[{"deploymentName":"Tacoma","deviceFriendlyName":"Foss High School","msrDeviceNbr":"2200","readingDateTimeUTC":"2022-05-05 21:28:24","readingDateTimeLocal":"2022-05-05 14:28:24","latitude":47.24,"longitude":-122.4963889,"cellTowerAddress":"","tempC":13.148193359375,"humidity":73.992919921875,"pressure":99408.703125,"pM25":2.2152621746063232,"pM10":3.781099319458008,"pM1":0.5702023506164551,"vBattery":4.163906097412109,"cellSignal":-90,"fwVersion":"","aqi":9,"aqiLabel":"Good","calibratedPM25":0,"calibrationVersion":""}]