[{"deploymentName":"Tacoma","deviceFriendlyName":"Larchmont Elementary School","msrDeviceNbr":"2204","readingDateTimeUTC":"2022-05-08 04:34:56","readingDateTimeLocal":"2022-05-07 21:34:56","latitude":47.17861111,"longitude":-122.4275,"cellTowerAddress":"","tempC":7.5299072265625,"humidity":68.3197021484375,"pressure":99797.234375,"pM25":4.184317588806152,"pM10":4.184314727783203,"pM1":3.956942558288574,"vBattery":4.190781116485596,"cellSignal":-107,"fwVersion":"","aqi":17,"aqiLabel":"Good","calibratedPM25":0,"calibrationVersion":""}]