[{"deploymentName":"Tacoma","deviceFriendlyName":"Crescent Heights Elementary School","msrDeviceNbr":"2189","readingDateTimeUTC":"2022-05-29 12:07:44","readingDateTimeLocal":"2022-05-29 05:07:44","latitude":47.29472222,"longitude":-122.4,"cellTowerAddress":"","tempC":11.604766845703125,"humidity":83.5052490234375,"pressure":99591.0625,"pM25":3.4546096324920654,"pM10":3.4546072483062744,"pM1":3.266887903213501,"vBattery":4.16796875,"cellSignal":-99,"fwVersion":"","aqi":14,"aqiLabel":"Good","calibratedPM25":3.4546096324920654,"calibrationVersion":"None"},{"deploymentName":"Tacoma","deviceFriendlyName":"Crescent Heights Elementary School","msrDeviceNbr":"2189","readingDateTimeUTC":"2022-05-29 11:47:33","readingDateTimeLocal":"2022-05-29 04:47:33","latitude":47.29472222,"longitude":-122.4,"cellTowerAddress":"","tempC":11.596755981445312,"humidity":83.880615234375,"pressure":99580.0078125,"pM25":2.756526470184326,"pM10":2.7565245628356934,"pM1":2.6067380905151367,"vBattery":4.166874885559082,"cellSignal":-99,"fwVersion":"","aqi":11,"aqiLabel":"Good","calibratedPM25":2.756526470184326,"calibrationVersion":"None"},{"deploymentName":"Tacoma","deviceFriendlyName":"Crescent Heights Elementary School","msrDeviceNbr":"2189","readingDateTimeUTC":"2022-05-29 11:27:22","readingDateTimeLocal":"2022-05-29 04:27:22","latitude":47.29472222,"longitude":-122.4,"cellTowerAddress":"","tempC":11.53533935546875,"humidity":83.7646484375,"pressure":99557.3515625,"pM25":3.8520801067352295,"pM10":5.815567493438721,"pM1":2.1462578773498535,"vBattery":4.16796875,"cellSignal":-99,"fwVersion":"","aqi":16,"aqiLabel":"Good","calibratedPM25":3.8520801067352295,"calibrationVersion":"None"},{"deploymentName":"Tacoma","deviceFriendlyName":"Crescent Heights Elementary School","msrDeviceNbr":"2189","readingDateTimeUTC":"2022-05-29 11:07:11","readingDateTimeLocal":"2022-05-29 04:07:11","latitude":47.29472222,"longitude":-122.4,"cellTowerAddress":"","tempC":11.44989013671875,"humidity":83.25042724609375,"pressure":99541.0078125,"pM25":2.5730223655700684,"pM10":2.5730206966400146,"pM1":2.4332056045532227,"vBattery":4.168124675750732,"cellSignal":-99,"fwVersion":"","aqi":10,"aqiLabel":"Good","calibratedPM25":2.5730223655700684,"calibrationVersion":"None"},{"deploymentName":"Tacoma","deviceFriendlyName":"Crescent Heights Elementary School","msrDeviceNbr":"2189","readingDateTimeUTC":"2022-05-29 10:46:59","readingDateTimeLocal":"2022-05-29 03:46:59","latitude":47.29472222,"longitude":-122.4,"cellTowerAddress":"","tempC":11.6741943359375,"humidity":82.85369873046875,"pressure":99524.6796875,"pM25":1.0402257442474365,"pM10":1.0402250289916992,"pM1":0.9837003350257874,"vBattery":4.169062614440918,"cellSignal":-99,"fwVersion":"","aqi":4,"aqiLabel":"Good","calibratedPM25":1.0402257442474365,"calibrationVersion":"None"},{"deploymentName":"Tacoma","deviceFriendlyName":"Crescent Heights Elementary School","msrDeviceNbr":"2189","readingDateTimeUTC":"2022-05-29 10:26:48","readingDateTimeLocal":"2022-05-29 03:26:48","latitude":47.29472222,"longitude":-122.4,"cellTowerAddress":"","tempC":11.82373046875,"humidity":82.92083740234375,"pressure":99511.3359375,"pM25":3.93784499168396,"pM10":3.93784236907959,"pM1":3.7238643169403076,"vBattery":4.167500019073486,"cellSignal":-99,"fwVersion":"","aqi":16,"aqiLabel":"Good","calibratedPM25":3.93784499168396,"calibrationVersion":"None"},{"deploymentName":"Tacoma","deviceFriendlyName":"Crescent Heights Elementary School","msrDeviceNbr":"2189","readingDateTimeUTC":"2022-05-29 10:06:37","readingDateTimeLocal":"2022-05-29 03:06:37","latitude":47.29472222,"longitude":-122.4,"cellTowerAddress":"","tempC":11.794357299804688,"humidity":82.95135498046875,"pressure":99486.1015625,"pM25":2.612061023712158,"pM10":2.6120591163635254,"pM1":2.470122814178467,"vBattery":4.168281078338623,"cellSignal":-99,"fwVersion":"","aqi":10,"aqiLabel":"Good","calibratedPM25":2.612061023712158,"calibrationVersion":"None"},{"deploymentName":"Tacoma","deviceFriendlyName":"Crescent Heights Elementary School","msrDeviceNbr":"2189","readingDateTimeUTC":"2022-05-29 09:46:25","readingDateTimeLocal":"2022-05-29 02:46:25","latitude":47.29472222,"longitude":-122.4,"cellTowerAddress":"","tempC":11.847763061523438,"humidity":82.8704833984375,"pressure":99475.5,"pM25":3.241894245147705,"pM10":3.8240697383880615,"pM1":2.6220173835754395,"vBattery":4.168749809265137,"cellSignal":-99,"fwVersion":"","aqi":13,"aqiLabel":"Good","calibratedPM25":3.241894245147705,"calibrationVersion":"None"},{"deploymentName":"Tacoma","deviceFriendlyName":"Crescent Heights Elementary School","msrDeviceNbr":"2189","readingDateTimeUTC":"2022-05-29 09:26:14","readingDateTimeLocal":"2022-05-29 02:26:14","latitude":47.29472222,"longitude":-122.4,"cellTowerAddress":"","tempC":11.917190551757812,"humidity":82.8125,"pressure":99450.7890625,"pM25":2.1327598094940186,"pM10":2.132758378982544,"pM1":2.016866683959961,"vBattery":4.16921854019165,"cellSignal":-99,"fwVersion":"","aqi":8,"aqiLabel":"Good","calibratedPM25":2.1327598094940186,"calibrationVersion":"None"},{"deploymentName":"Tacoma","deviceFriendlyName":"Crescent Heights Elementary School","msrDeviceNbr":"2189","readingDateTimeUTC":"2022-05-29 09:06:03","readingDateTimeLocal":"2022-05-29 02:06:03","latitude":47.29472222,"longitude":-122.4,"cellTowerAddress":"","tempC":11.82373046875,"humidity":82.80181884765625,"pressure":99440.1484375,"pM25":2.8495662212371826,"pM10":3.6840765476226807,"pM1":2.058687448501587,"vBattery":4.169687271118164,"cellSignal":-99,"fwVersion":"","aqi":11,"aqiLabel":"Good","calibratedPM25":2.8495662212371826,"calibrationVersion":"None"},{"deploymentName":"Tacoma","deviceFriendlyName":"Crescent Heights Elementary School","msrDeviceNbr":"2189","readingDateTimeUTC":"2022-05-29 08:45:52","readingDateTimeLocal":"2022-05-29 01:45:52","latitude":47.29472222,"longitude":-122.4,"cellTowerAddress":"","tempC":11.73828125,"humidity":82.67974853515625,"pressure":99418.96875,"pM25":3.2665257453918457,"pM10":3.266523599624634,"pM1":3.089024305343628,"vBattery":4.170000076293945,"cellSignal":-99,"fwVersion":"","aqi":13,"aqiLabel":"Good","calibratedPM25":3.2665257453918457,"calibrationVersion":"None"},{"deploymentName":"Tacoma","deviceFriendlyName":"Crescent Heights Elementary School","msrDeviceNbr":"2189","readingDateTimeUTC":"2022-05-29 08:25:41","readingDateTimeLocal":"2022-05-29 01:25:41","latitude":47.29472222,"longitude":-122.4,"cellTowerAddress":"","tempC":11.543350219726562,"humidity":82.13348388671875,"pressure":99395.015625,"pM25":3.527160882949829,"pM10":3.527158498764038,"pM1":3.335496664047241,"vBattery":4.170624732971191,"cellSignal":-99,"fwVersion":"","aqi":14,"aqiLabel":"Good","calibratedPM25":3.527160882949829,"calibrationVersion":"None"},{"deploymentName":"Tacoma","deviceFriendlyName":"Crescent Heights Elementary School","msrDeviceNbr":"2189","readingDateTimeUTC":"2022-05-29 08:05:29","readingDateTimeLocal":"2022-05-29 01:05:29","latitude":47.29472222,"longitude":-122.4,"cellTowerAddress":"","tempC":11.794357299804688,"humidity":81.72607421875,"pressure":99380.796875,"pM25":10.406648635864258,"pM10":16.701007843017578,"pM1":5.043816566467285,"vBattery":4.170156002044678,"cellSignal":-100,"fwVersion":"","aqi":43,"aqiLabel":"Good","calibratedPM25":10.406648635864258,"calibrationVersion":"None"},{"deploymentName":"Tacoma","deviceFriendlyName":"Crescent Heights Elementary School","msrDeviceNbr":"2189","readingDateTimeUTC":"2022-05-29 07:45:18","readingDateTimeLocal":"2022-05-29 00:45:18","latitude":47.29472222,"longitude":-122.4,"cellTowerAddress":"","tempC":12.080078125,"humidity":80.85784912109375,"pressure":99358.578125,"pM25":2.072937250137329,"pM10":2.0729358196258545,"pM1":1.9602948427200317,"vBattery":4.170156002044678,"cellSignal":-99,"fwVersion":"","aqi":8,"aqiLabel":"Good","calibratedPM25":2.072937250137329,"calibrationVersion":"None"},{"deploymentName":"Tacoma","deviceFriendlyName":"Crescent Heights Elementary School","msrDeviceNbr":"2189","readingDateTimeUTC":"2022-05-29 07:25:07","readingDateTimeLocal":"2022-05-29 00:25:07","latitude":47.29472222,"longitude":-122.4,"cellTowerAddress":"","tempC":12.408523559570312,"humidity":80.58319091796875,"pressure":99337.28125,"pM25":2.396782398223877,"pM10":3.2779381275177,"pM1":1.5949562788009644,"vBattery":4.170781135559082,"cellSignal":-100,"fwVersion":"","aqi":9,"aqiLabel":"Good","calibratedPM25":2.396782398223877,"calibrationVersion":"None"},{"deploymentName":"Tacoma","deviceFriendlyName":"Crescent Heights Elementary School","msrDeviceNbr":"2189","readingDateTimeUTC":"2022-05-29 07:04:56","readingDateTimeLocal":"2022-05-29 00:04:56","latitude":47.29472222,"longitude":-122.4,"cellTowerAddress":"","tempC":12.627487182617188,"humidity":80.57708740234375,"pressure":99320.359375,"pM25":1.802675724029541,"pM10":2.1608309745788574,"pM1":1.4317439794540405,"vBattery":4.170624732971191,"cellSignal":-100,"fwVersion":"","aqi":7,"aqiLabel":"Good","calibratedPM25":1.802675724029541,"calibrationVersion":"None"},{"deploymentName":"Tacoma","deviceFriendlyName":"Crescent Heights Elementary School","msrDeviceNbr":"2189","readingDateTimeUTC":"2022-05-29 06:44:45","readingDateTimeLocal":"2022-05-28 23:44:45","latitude":47.29472222,"longitude":-122.4,"cellTowerAddress":"","tempC":12.515335083007812,"humidity":80.6884765625,"pressure":99296.125,"pM25":1.5415148735046387,"pM10":1.5415138006210327,"pM1":1.4577497243881226,"vBattery":4.171249866485596,"cellSignal":-100,"fwVersion":"","aqi":6,"aqiLabel":"Good","calibratedPM25":1.5415148735046387,"calibrationVersion":"None"},{"deploymentName":"Tacoma","deviceFriendlyName":"Crescent Heights Elementary School","msrDeviceNbr":"2189","readingDateTimeUTC":"2022-05-29 06:24:34","readingDateTimeLocal":"2022-05-28 23:24:34","latitude":47.29472222,"longitude":-122.4,"cellTowerAddress":"","tempC":12.416534423828125,"humidity":80.523681640625,"pressure":99278.9921875,"pM25":0.8721149563789368,"pM10":0.872114360332489,"pM1":0.8247246146202087,"vBattery":4.171093463897705,"cellSignal":-100,"fwVersion":"","aqi":3,"aqiLabel":"Good","calibratedPM25":0.8721149563789368,"calibrationVersion":"None"},{"deploymentName":"Tacoma","deviceFriendlyName":"Crescent Heights Elementary School","msrDeviceNbr":"2189","readingDateTimeUTC":"2022-05-29 06:04:22","readingDateTimeLocal":"2022-05-28 23:04:22","latitude":47.29472222,"longitude":-122.4,"cellTowerAddress":"","tempC":12.416534423828125,"humidity":80.55877685546875,"pressure":99259.9765625,"pM25":1.18043851852417,"pM10":1.1804378032684326,"pM1":1.1162941455841064,"vBattery":4.171093463897705,"cellSignal":-100,"fwVersion":"","aqi":4,"aqiLabel":"Good","calibratedPM25":1.18043851852417,"calibrationVersion":"None"},{"deploymentName":"Tacoma","deviceFriendlyName":"Crescent Heights Elementary School","msrDeviceNbr":"2189","readingDateTimeUTC":"2022-05-29 05:44:11","readingDateTimeLocal":"2022-05-28 22:44:11","latitude":47.29472222,"longitude":-122.4,"cellTowerAddress":"","tempC":12.291030883789062,"humidity":80.8197021484375,"pressure":99233.4765625,"pM25":4.633508205413818,"pM10":4.633504867553711,"pM1":4.381725788116455,"vBattery":4.172343730926514,"cellSignal":-100,"fwVersion":"","aqi":19,"aqiLabel":"Good","calibratedPM25":4.633508205413818,"calibrationVersion":"None"},{"deploymentName":"Tacoma","deviceFriendlyName":"Crescent Heights Elementary School","msrDeviceNbr":"2189","readingDateTimeUTC":"2022-05-29 05:24:00","readingDateTimeLocal":"2022-05-28 22:24:00","latitude":47.29472222,"longitude":-122.4,"cellTowerAddress":"","tempC":12.237625122070312,"humidity":80.40771484375,"pressure":99218.7890625,"pM25":1.7635682821273804,"pM10":1.7635670900344849,"pM1":1.6677368879318237,"vBattery":4.172968864440918,"cellSignal":-100,"fwVersion":"","aqi":7,"aqiLabel":"Good","calibratedPM25":1.7635682821273804,"calibrationVersion":"None"},{"deploymentName":"Tacoma","deviceFriendlyName":"Crescent Heights Elementary School","msrDeviceNbr":"2189","readingDateTimeUTC":"2022-05-29 05:03:49","readingDateTimeLocal":"2022-05-28 22:03:49","latitude":47.29472222,"longitude":-122.4,"cellTowerAddress":"","tempC":12.237625122070312,"humidity":81.17828369140625,"pressure":99186.28125,"pM25":3.171001672744751,"pM10":3.170999526977539,"pM1":2.9986910820007324,"vBattery":4.173593521118164,"cellSignal":-99,"fwVersion":"","aqi":13,"aqiLabel":"Good","calibratedPM25":3.171001672744751,"calibrationVersion":"None"},{"deploymentName":"Tacoma","deviceFriendlyName":"Crescent Heights Elementary School","msrDeviceNbr":"2189","readingDateTimeUTC":"2022-05-29 04:43:37","readingDateTimeLocal":"2022-05-28 21:43:37","latitude":47.29472222,"longitude":-122.4,"cellTowerAddress":"","tempC":12.04803466796875,"humidity":80.670166015625,"pressure":99150.6171875,"pM25":2.374702215194702,"pM10":4.052610397338867,"pM1":0.9668180346488953,"vBattery":4.173906326293945,"cellSignal":-99,"fwVersion":"","aqi":9,"aqiLabel":"Good","calibratedPM25":2.374702215194702,"calibrationVersion":"None"},{"deploymentName":"Tacoma","deviceFriendlyName":"Crescent Heights Elementary School","msrDeviceNbr":"2189","readingDateTimeUTC":"2022-05-29 04:23:26","readingDateTimeLocal":"2022-05-28 21:23:26","latitude":47.29472222,"longitude":-122.4,"cellTowerAddress":"","tempC":12.323074340820312,"humidity":80.93719482421875,"pressure":99140.9296875,"pM25":4.22471809387207,"pM10":5.254700660705566,"pM1":3.210129737854004,"vBattery":4.173593521118164,"cellSignal":-99,"fwVersion":"","aqi":17,"aqiLabel":"Good","calibratedPM25":4.22471809387207,"calibrationVersion":"None"},{"deploymentName":"Tacoma","deviceFriendlyName":"Crescent Heights Elementary School","msrDeviceNbr":"2189","readingDateTimeUTC":"2022-05-29 04:03:15","readingDateTimeLocal":"2022-05-28 21:03:15","latitude":47.29472222,"longitude":-122.4,"cellTowerAddress":"","tempC":12.19757080078125,"humidity":81.16302490234375,"pressure":99132.984375,"pM25":1.510441541671753,"pM10":1.510440468788147,"pM1":1.428364872932434,"vBattery":4.175156116485596,"cellSignal":-99,"fwVersion":"","aqi":6,"aqiLabel":"Good","calibratedPM25":1.510441541671753,"calibrationVersion":"None"},{"deploymentName":"Tacoma","deviceFriendlyName":"Crescent Heights Elementary School","msrDeviceNbr":"2189","readingDateTimeUTC":"2022-05-29 03:43:04","readingDateTimeLocal":"2022-05-28 20:43:04","latitude":47.29472222,"longitude":-122.4,"cellTowerAddress":"","tempC":12.117462158203125,"humidity":80.86700439453125,"pressure":99129.1796875,"pM25":1.301419973373413,"pM10":1.8307266235351562,"pM1":0.8272824883460999,"vBattery":4.175624847412109,"cellSignal":-99,"fwVersion":"","aqi":5,"aqiLabel":"Good","calibratedPM25":1.301419973373413,"calibrationVersion":"None"},{"deploymentName":"Tacoma","deviceFriendlyName":"Crescent Heights Elementary School","msrDeviceNbr":"2189","readingDateTimeUTC":"2022-05-29 03:22:53","readingDateTimeLocal":"2022-05-28 20:22:53","latitude":47.29472222,"longitude":-122.4,"cellTowerAddress":"","tempC":11.917190551757812,"humidity":80.81512451171875,"pressure":99122.8203125,"pM25":3.2507448196411133,"pM10":4.656397342681885,"pM1":2.002760887145996,"vBattery":4.175624847412109,"cellSignal":-99,"fwVersion":"","aqi":13,"aqiLabel":"Good","calibratedPM25":3.2507448196411133,"calibrationVersion":"None"},{"deploymentName":"Tacoma","deviceFriendlyName":"Crescent Heights Elementary School","msrDeviceNbr":"2189","readingDateTimeUTC":"2022-05-29 03:02:41","readingDateTimeLocal":"2022-05-28 20:02:41","latitude":47.29472222,"longitude":-122.4,"cellTowerAddress":"","tempC":12.28302001953125,"humidity":79.644775390625,"pressure":99097.9140625,"pM25":4.641502857208252,"pM10":7.412745952606201,"pM1":2.2771403789520264,"vBattery":4.175937175750732,"cellSignal":-99,"fwVersion":"","aqi":19,"aqiLabel":"Good","calibratedPM25":4.641502857208252,"calibrationVersion":"None"},{"deploymentName":"Tacoma","deviceFriendlyName":"Crescent Heights Elementary School","msrDeviceNbr":"2189","readingDateTimeUTC":"2022-05-29 02:42:30","readingDateTimeLocal":"2022-05-28 19:42:30","latitude":47.29472222,"longitude":-122.4,"cellTowerAddress":"","tempC":12.352447509765625,"humidity":78.8726806640625,"pressure":99081.84375,"pM25":0.7039889097213745,"pM10":0.7039884328842163,"pM1":0.6657345294952393,"vBattery":4.177187442779541,"cellSignal":-99,"fwVersion":"","aqi":2,"aqiLabel":"Good","calibratedPM25":0.7039889097213745,"calibrationVersion":"None"},{"deploymentName":"Tacoma","deviceFriendlyName":"Crescent Heights Elementary School","msrDeviceNbr":"2189","readingDateTimeUTC":"2022-05-29 02:22:19","readingDateTimeLocal":"2022-05-28 19:22:19","latitude":47.29472222,"longitude":-122.4,"cellTowerAddress":"","tempC":12.79571533203125,"humidity":78.3935546875,"pressure":99082.96875,"pM25":0.770469069480896,"pM10":0.770468533039093,"pM1":0.7286021709442139,"vBattery":4.176406383514404,"cellSignal":-98,"fwVersion":"","aqi":3,"aqiLabel":"Good","calibratedPM25":0.770469069480896,"calibrationVersion":"None"},{"deploymentName":"Tacoma","deviceFriendlyName":"Crescent Heights Elementary School","msrDeviceNbr":"2189","readingDateTimeUTC":"2022-05-29 02:02:08","readingDateTimeLocal":"2022-05-28 19:02:08","latitude":47.29472222,"longitude":-122.4,"cellTowerAddress":"","tempC":13.070755004882812,"humidity":78.1829833984375,"pressure":99067.0546875,"pM25":3.279545783996582,"pM10":4.673375129699707,"pM1":2.0390093326568604,"vBattery":4.177968502044678,"cellSignal":-99,"fwVersion":"","aqi":13,"aqiLabel":"Good","calibratedPM25":3.279545783996582,"calibrationVersion":"None"},{"deploymentName":"Tacoma","deviceFriendlyName":"Crescent Heights Elementary School","msrDeviceNbr":"2189","readingDateTimeUTC":"2022-05-29 01:41:57","readingDateTimeLocal":"2022-05-28 18:41:57","latitude":47.29472222,"longitude":-122.4,"cellTowerAddress":"","tempC":13.348464965820312,"humidity":77.25830078125,"pressure":99072.390625,"pM25":0.7962304949760437,"pM10":0.7962299585342407,"pM1":0.7529637217521667,"vBattery":4.177187442779541,"cellSignal":-99,"fwVersion":"","aqi":3,"aqiLabel":"Good","calibratedPM25":0.7962304949760437,"calibrationVersion":"None"},{"deploymentName":"Tacoma","deviceFriendlyName":"Crescent Heights Elementary School","msrDeviceNbr":"2189","readingDateTimeUTC":"2022-05-29 01:21:45","readingDateTimeLocal":"2022-05-28 18:21:45","latitude":47.29472222,"longitude":-122.4,"cellTowerAddress":"","tempC":13.676910400390625,"humidity":77.38189697265625,"pressure":99079.6484375,"pM25":4.225780487060547,"pM10":5.95586633682251,"pM1":2.6775407791137695,"vBattery":4.176718711853027,"cellSignal":-99,"fwVersion":"","aqi":17,"aqiLabel":"Good","calibratedPM25":4.225780487060547,"calibrationVersion":"None"},{"deploymentName":"Tacoma","deviceFriendlyName":"Crescent Heights Elementary School","msrDeviceNbr":"2189","readingDateTimeUTC":"2022-05-29 01:01:34","readingDateTimeLocal":"2022-05-28 18:01:34","latitude":47.29472222,"longitude":-122.4,"cellTowerAddress":"","tempC":13.775711059570312,"humidity":77.1087646484375,"pressure":99082.90625,"pM25":1.6127737760543823,"pM10":2.466291904449463,"pM1":0.8746140599250793,"vBattery":4.174843788146973,"cellSignal":-98,"fwVersion":"","aqi":6,"aqiLabel":"Good","calibratedPM25":1.6127737760543823,"calibrationVersion":"None"},{"deploymentName":"Tacoma","deviceFriendlyName":"Crescent Heights Elementary School","msrDeviceNbr":"2189","readingDateTimeUTC":"2022-05-29 00:41:23","readingDateTimeLocal":"2022-05-28 17:41:23","latitude":47.29472222,"longitude":-122.4,"cellTowerAddress":"","tempC":13.823776245117188,"humidity":75.518798828125,"pressure":99080.0234375,"pM25":1.764723777770996,"pM10":2.8173646926879883,"pM1":0.8665422797203064,"vBattery":4.176249980926514,"cellSignal":-99,"fwVersion":"","aqi":7,"aqiLabel":"Good","calibratedPM25":1.764723777770996,"calibrationVersion":"None"},{"deploymentName":"Tacoma","deviceFriendlyName":"Crescent Heights Elementary School","msrDeviceNbr":"2189","readingDateTimeUTC":"2022-05-29 00:21:12","readingDateTimeLocal":"2022-05-28 17:21:12","latitude":47.29472222,"longitude":-122.4,"cellTowerAddress":"","tempC":14.347152709960938,"humidity":74.591064453125,"pressure":99065.0546875,"pM25":1.0326991081237793,"pM10":1.273887276649475,"pM1":0.7927571535110474,"vBattery":4.17578125,"cellSignal":-99,"fwVersion":"","aqi":4,"aqiLabel":"Good","calibratedPM25":1.0326991081237793,"calibrationVersion":"None"},{"deploymentName":"Tacoma","deviceFriendlyName":"Crescent Heights Elementary School","msrDeviceNbr":"2189","readingDateTimeUTC":"2022-05-29 00:01:01","readingDateTimeLocal":"2022-05-28 17:01:01","latitude":47.29472222,"longitude":-122.4,"cellTowerAddress":"","tempC":14.843826293945312,"humidity":74.420166015625,"pressure":99058.09375,"pM25":4.718493461608887,"pM10":7.624243259429932,"pM1":2.247429847717285,"vBattery":4.175156116485596,"cellSignal":-99,"fwVersion":"","aqi":19,"aqiLabel":"Good","calibratedPM25":4.718493461608887,"calibrationVersion":"None"},{"deploymentName":"Tacoma","deviceFriendlyName":"Crescent Heights Elementary School","msrDeviceNbr":"2189","readingDateTimeUTC":"2022-05-28 23:40:50","readingDateTimeLocal":"2022-05-28 16:40:50","latitude":47.29472222,"longitude":-122.4,"cellTowerAddress":"","tempC":15.287094116210938,"humidity":73.43597412109375,"pressure":99058.59375,"pM25":1.2817487716674805,"pM10":1.281747817993164,"pM1":1.2120990753173828,"vBattery":4.172968864440918,"cellSignal":-99,"fwVersion":"","aqi":5,"aqiLabel":"Good","calibratedPM25":1.2817487716674805,"calibrationVersion":"None"},{"deploymentName":"Tacoma","deviceFriendlyName":"Crescent Heights Elementary School","msrDeviceNbr":"2189","readingDateTimeUTC":"2022-05-28 23:20:38","readingDateTimeLocal":"2022-05-28 16:20:38","latitude":47.29472222,"longitude":-122.4,"cellTowerAddress":"","tempC":15.225677490234375,"humidity":72.0611572265625,"pressure":99078.609375,"pM25":2.8751957416534424,"pM10":4.498598575592041,"pM1":1.4816566705703735,"vBattery":4.171875,"cellSignal":-100,"fwVersion":"","aqi":11,"aqiLabel":"Good","calibratedPM25":2.8751957416534424,"calibrationVersion":"None"},{"deploymentName":"Tacoma","deviceFriendlyName":"Crescent Heights Elementary School","msrDeviceNbr":"2189","readingDateTimeUTC":"2022-05-28 23:00:27","readingDateTimeLocal":"2022-05-28 16:00:27","latitude":47.29472222,"longitude":-122.4,"cellTowerAddress":"","tempC":15.474014282226562,"humidity":71.4996337890625,"pressure":99088.1875,"pM25":1.3436975479125977,"pM10":1.8693279027938843,"pM1":0.8700643181800842,"vBattery":4.176718711853027,"cellSignal":-100,"fwVersion":"","aqi":5,"aqiLabel":"Good","calibratedPM25":1.3436975479125977,"calibrationVersion":"None"},{"deploymentName":"Tacoma","deviceFriendlyName":"Crescent Heights Elementary School","msrDeviceNbr":"2189","readingDateTimeUTC":"2022-05-28 22:40:16","readingDateTimeLocal":"2022-05-28 15:40:16","latitude":47.29472222,"longitude":-122.4,"cellTowerAddress":"","tempC":15.5194091796875,"humidity":70.4376220703125,"pressure":99097.96875,"pM25":4.872862339019775,"pM10":8.658369064331055,"pM1":1.722890019416809,"vBattery":4.173281192779541,"cellSignal":-100,"fwVersion":"","aqi":20,"aqiLabel":"Good","calibratedPM25":4.872862339019775,"calibrationVersion":"None"},{"deploymentName":"Tacoma","deviceFriendlyName":"Crescent Heights Elementary School","msrDeviceNbr":"2189","readingDateTimeUTC":"2022-05-28 22:20:04","readingDateTimeLocal":"2022-05-28 15:20:04","latitude":47.29472222,"longitude":-122.4,"cellTowerAddress":"","tempC":15.527420043945312,"humidity":68.88885498046875,"pressure":99098.875,"pM25":4.011839866638184,"pM10":5.420629024505615,"pM1":2.720109462738037,"vBattery":4.17312479019165,"cellSignal":-100,"fwVersion":"","aqi":16,"aqiLabel":"Good","calibratedPM25":4.011839866638184,"calibrationVersion":"None"},{"deploymentName":"Tacoma","deviceFriendlyName":"Crescent Heights Elementary School","msrDeviceNbr":"2189","readingDateTimeUTC":"2022-05-28 21:59:53","readingDateTimeLocal":"2022-05-28 14:59:53","latitude":47.29472222,"longitude":-122.4,"cellTowerAddress":"","tempC":16.221694946289062,"humidity":67.25311279296875,"pressure":99121.1796875,"pM25":2.402745008468628,"pM10":3.412666082382202,"pM1":1.502453327178955,"vBattery":4.175937175750732,"cellSignal":-100,"fwVersion":"","aqi":10,"aqiLabel":"Good","calibratedPM25":2.402745008468628,"calibrationVersion":"None"},{"deploymentName":"Tacoma","deviceFriendlyName":"Crescent Heights Elementary School","msrDeviceNbr":"2189","readingDateTimeUTC":"2022-05-28 21:39:41","readingDateTimeLocal":"2022-05-28 14:39:41","latitude":47.29472222,"longitude":-122.4,"cellTowerAddress":"","tempC":16.526107788085938,"humidity":65.875244140625,"pressure":99147.15625,"pM25":3.6822586059570312,"pM10":4.867307662963867,"pM1":2.578961133956909,"vBattery":4.172968864440918,"cellSignal":-100,"fwVersion":"","aqi":15,"aqiLabel":"Good","calibratedPM25":3.6822586059570312,"calibrationVersion":"None"},{"deploymentName":"Tacoma","deviceFriendlyName":"Crescent Heights Elementary School","msrDeviceNbr":"2189","readingDateTimeUTC":"2022-05-28 21:19:30","readingDateTimeLocal":"2022-05-28 14:19:30","latitude":47.29472222,"longitude":-122.4,"cellTowerAddress":"","tempC":17.514114379882812,"humidity":64.90325927734375,"pressure":99167.0234375,"pM25":2.071851968765259,"pM10":2.071850538253784,"pM1":1.9592684507369995,"vBattery":4.172812461853027,"cellSignal":-100,"fwVersion":"","aqi":8,"aqiLabel":"Good","calibratedPM25":2.071851968765259,"calibrationVersion":"None"},{"deploymentName":"Tacoma","deviceFriendlyName":"Crescent Heights Elementary School","msrDeviceNbr":"2189","readingDateTimeUTC":"2022-05-28 20:59:19","readingDateTimeLocal":"2022-05-28 13:59:19","latitude":47.29472222,"longitude":-122.4,"cellTowerAddress":"","tempC":18.515472412109375,"humidity":65.12451171875,"pressure":99180.8359375,"pM25":3.346688747406006,"pM10":5.510331630706787,"pM1":1.5157767534255981,"vBattery":4.168593883514404,"cellSignal":-100,"fwVersion":"","aqi":13,"aqiLabel":"Good","calibratedPM25":3.346688747406006,"calibrationVersion":"None"},{"deploymentName":"Tacoma","deviceFriendlyName":"Crescent Heights Elementary School","msrDeviceNbr":"2189","readingDateTimeUTC":"2022-05-28 20:39:08","readingDateTimeLocal":"2022-05-28 13:39:08","latitude":47.29472222,"longitude":-122.4,"cellTowerAddress":"","tempC":18.462066650390625,"humidity":66.7327880859375,"pressure":99198.7421875,"pM25":1.5401767492294312,"pM10":1.5401756763458252,"pM1":1.456484317779541,"vBattery":4.167187213897705,"cellSignal":-100,"fwVersion":"","aqi":6,"aqiLabel":"Good","calibratedPM25":1.5401767492294312,"calibrationVersion":"None"},{"deploymentName":"Tacoma","deviceFriendlyName":"Crescent Heights Elementary School","msrDeviceNbr":"2189","readingDateTimeUTC":"2022-05-28 20:18:57","readingDateTimeLocal":"2022-05-28 13:18:57","latitude":47.29472222,"longitude":-122.4,"cellTowerAddress":"","tempC":18.048171997070312,"humidity":65.4022216796875,"pressure":99209.8046875,"pM25":1.5440505743026733,"pM10":2.2865333557128906,"pM1":0.8942521810531616,"vBattery":4.168281078338623,"cellSignal":-100,"fwVersion":"","aqi":6,"aqiLabel":"Good","calibratedPM25":1.5440505743026733,"calibrationVersion":"None"},{"deploymentName":"Tacoma","deviceFriendlyName":"Crescent Heights Elementary School","msrDeviceNbr":"2189","readingDateTimeUTC":"2022-05-28 19:58:45","readingDateTimeLocal":"2022-05-28 12:58:45","latitude":47.29472222,"longitude":-122.4,"cellTowerAddress":"","tempC":18.026809692382812,"humidity":64.83154296875,"pressure":99242,"pM25":3.429178237915039,"pM10":3.429175853729248,"pM1":3.2428383827209473,"vBattery":4.167031288146973,"cellSignal":-100,"fwVersion":"","aqi":14,"aqiLabel":"Good","calibratedPM25":3.429178237915039,"calibrationVersion":"None"},{"deploymentName":"Tacoma","deviceFriendlyName":"Crescent Heights Elementary School","msrDeviceNbr":"2189","readingDateTimeUTC":"2022-05-28 19:38:34","readingDateTimeLocal":"2022-05-28 12:38:34","latitude":47.29472222,"longitude":-122.4,"cellTowerAddress":"","tempC":18.39263916015625,"humidity":63.30718994140625,"pressure":99257.1875,"pM25":2.6292290687561035,"pM10":2.6292271614074707,"pM1":2.4863579273223877,"vBattery":4.168593883514404,"cellSignal":-100,"fwVersion":"","aqi":10,"aqiLabel":"Good","calibratedPM25":2.6292290687561035,"calibrationVersion":"None"},{"deploymentName":"Tacoma","deviceFriendlyName":"Crescent Heights Elementary School","msrDeviceNbr":"2189","readingDateTimeUTC":"2022-05-28 19:18:23","readingDateTimeLocal":"2022-05-28 12:18:23","latitude":47.29472222,"longitude":-122.4,"cellTowerAddress":"","tempC":18.515472412109375,"humidity":63.18359375,"pressure":99275.8828125,"pM25":0.7965099811553955,"pM10":0.7965094447135925,"pM1":0.7532280087471008,"vBattery":4.168593883514404,"cellSignal":-100,"fwVersion":"","aqi":3,"aqiLabel":"Good","calibratedPM25":0.7965099811553955,"calibrationVersion":"None"},{"deploymentName":"Tacoma","deviceFriendlyName":"Crescent Heights Elementary School","msrDeviceNbr":"2189","readingDateTimeUTC":"2022-05-28 18:58:12","readingDateTimeLocal":"2022-05-28 11:58:12","latitude":47.29472222,"longitude":-122.4,"cellTowerAddress":"","tempC":19.132308959960938,"humidity":62.92724609375,"pressure":99308.4140625,"pM25":2.572676420211792,"pM10":3.1836133003234863,"pM1":1.967241883277893,"vBattery":4.167031288146973,"cellSignal":-101,"fwVersion":"","aqi":10,"aqiLabel":"Good","calibratedPM25":2.572676420211792,"calibrationVersion":"None"},{"deploymentName":"Tacoma","deviceFriendlyName":"Crescent Heights Elementary School","msrDeviceNbr":"2189","readingDateTimeUTC":"2022-05-28 18:38:01","readingDateTimeLocal":"2022-05-28 11:38:01","latitude":47.29472222,"longitude":-122.4,"cellTowerAddress":"","tempC":18.889312744140625,"humidity":65.5731201171875,"pressure":99318.546875,"pM25":1.4004098176956177,"pM10":1.4004088640213013,"pM1":1.3243122100830078,"vBattery":4.168124675750732,"cellSignal":-101,"fwVersion":"","aqi":5,"aqiLabel":"Good","calibratedPM25":1.4004098176956177,"calibrationVersion":"None"},{"deploymentName":"Tacoma","deviceFriendlyName":"Crescent Heights Elementary School","msrDeviceNbr":"2189","readingDateTimeUTC":"2022-05-28 18:17:49","readingDateTimeLocal":"2022-05-28 11:17:49","latitude":47.29472222,"longitude":-122.4,"cellTowerAddress":"","tempC":18.026809692382812,"humidity":68.0877685546875,"pressure":99344.7265625,"pM25":1.4151039123535156,"pM10":1.4151029586791992,"pM1":1.3382078409194946,"vBattery":4.167187213897705,"cellSignal":-101,"fwVersion":"","aqi":5,"aqiLabel":"Good","calibratedPM25":1.4151039123535156,"calibrationVersion":"None"},{"deploymentName":"Tacoma","deviceFriendlyName":"Crescent Heights Elementary School","msrDeviceNbr":"2189","readingDateTimeUTC":"2022-05-28 17:57:38","readingDateTimeLocal":"2022-05-28 10:57:38","latitude":47.29472222,"longitude":-122.4,"cellTowerAddress":"","tempC":16.77978515625,"humidity":69.45953369140625,"pressure":99367.0234375,"pM25":1.3798835277557373,"pM10":1.3798826932907104,"pM1":1.304901361465454,"vBattery":4.167812347412109,"cellSignal":-101,"fwVersion":"","aqi":5,"aqiLabel":"Good","calibratedPM25":1.3798835277557373,"calibrationVersion":"None"},{"deploymentName":"Tacoma","deviceFriendlyName":"Crescent Heights Elementary School","msrDeviceNbr":"2189","readingDateTimeUTC":"2022-05-28 17:37:27","readingDateTimeLocal":"2022-05-28 10:37:27","latitude":47.29472222,"longitude":-122.4,"cellTowerAddress":"","tempC":16.251068115234375,"humidity":70.3643798828125,"pressure":99385.6796875,"pM25":3.022092819213867,"pM10":4.003551483154297,"pM1":2.109837532043457,"vBattery":4.169843673706055,"cellSignal":-101,"fwVersion":"","aqi":12,"aqiLabel":"Good","calibratedPM25":3.022092819213867,"calibrationVersion":"None"},{"deploymentName":"Tacoma","deviceFriendlyName":"Crescent Heights Elementary School","msrDeviceNbr":"2189","readingDateTimeUTC":"2022-05-28 17:17:16","readingDateTimeLocal":"2022-05-28 10:17:16","latitude":47.29472222,"longitude":-122.4,"cellTowerAddress":"","tempC":16.034774780273438,"humidity":71.70867919921875,"pressure":99402.5,"pM25":1.9251340627670288,"pM10":2.8679728507995605,"pM1":1.1019238233566284,"vBattery":4.169531345367432,"cellSignal":-101,"fwVersion":"","aqi":8,"aqiLabel":"Good","calibratedPM25":1.9251340627670288,"calibrationVersion":"None"},{"deploymentName":"Tacoma","deviceFriendlyName":"Crescent Heights Elementary School","msrDeviceNbr":"2189","readingDateTimeUTC":"2022-05-28 16:57:05","readingDateTimeLocal":"2022-05-28 09:57:05","latitude":47.29472222,"longitude":-122.4,"cellTowerAddress":"","tempC":15.901260375976562,"humidity":70.74737548828125,"pressure":99420.5703125,"pM25":4.5768327713012695,"pM10":6.550416469573975,"pM1":2.8239316940307617,"vBattery":4.167500019073486,"cellSignal":-101,"fwVersion":"","aqi":19,"aqiLabel":"Good","calibratedPM25":4.5768327713012695,"calibrationVersion":"None"},{"deploymentName":"Tacoma","deviceFriendlyName":"Crescent Heights Elementary School","msrDeviceNbr":"2189","readingDateTimeUTC":"2022-05-28 16:36:53","readingDateTimeLocal":"2022-05-28 09:36:53","latitude":47.29472222,"longitude":-122.4,"cellTowerAddress":"","tempC":16.55548095703125,"humidity":69.04449462890625,"pressure":99439.1640625,"pM25":2.7558887004852295,"pM10":2.7558867931365967,"pM1":2.6061348915100098,"vBattery":4.170312404632568,"cellSignal":-101,"fwVersion":"","aqi":11,"aqiLabel":"Good","calibratedPM25":2.7558887004852295,"calibrationVersion":"None"},{"deploymentName":"Tacoma","deviceFriendlyName":"Crescent Heights Elementary School","msrDeviceNbr":"2189","readingDateTimeUTC":"2022-05-28 16:16:42","readingDateTimeLocal":"2022-05-28 09:16:42","latitude":47.29472222,"longitude":-122.4,"cellTowerAddress":"","tempC":16.397933959960938,"humidity":69.72198486328125,"pressure":99457.5859375,"pM25":3.22102689743042,"pM10":3.8370025157928467,"pM1":2.576521158218384,"vBattery":4.16796875,"cellSignal":-101,"fwVersion":"","aqi":13,"aqiLabel":"Good","calibratedPM25":3.22102689743042,"calibrationVersion":"None"},{"deploymentName":"Tacoma","deviceFriendlyName":"Crescent Heights Elementary School","msrDeviceNbr":"2189","readingDateTimeUTC":"2022-05-28 15:56:31","readingDateTimeLocal":"2022-05-28 08:56:31","latitude":47.29472222,"longitude":-122.4,"cellTowerAddress":"","tempC":16.168289184570312,"humidity":71.5606689453125,"pressure":99479.546875,"pM25":2.6105568408966064,"pM10":3.8068103790283203,"pM1":1.556957721710205,"vBattery":4.167500019073486,"cellSignal":-100,"fwVersion":"","aqi":10,"aqiLabel":"Good","calibratedPM25":2.6105568408966064,"calibrationVersion":"None"},{"deploymentName":"Tacoma","deviceFriendlyName":"Crescent Heights Elementary School","msrDeviceNbr":"2189","readingDateTimeUTC":"2022-05-28 15:36:19","readingDateTimeLocal":"2022-05-28 08:36:19","latitude":47.29472222,"longitude":-122.4,"cellTowerAddress":"","tempC":15.72235107421875,"humidity":73.93035888671875,"pressure":99483.3515625,"pM25":3.100996255874634,"pM10":3.100994110107422,"pM1":2.9324896335601807,"vBattery":4.168749809265137,"cellSignal":-100,"fwVersion":"","aqi":12,"aqiLabel":"Good","calibratedPM25":3.100996255874634,"calibrationVersion":"None"},{"deploymentName":"Tacoma","deviceFriendlyName":"Crescent Heights Elementary School","msrDeviceNbr":"2189","readingDateTimeUTC":"2022-05-28 15:16:08","readingDateTimeLocal":"2022-05-28 08:16:08","latitude":47.29472222,"longitude":-122.4,"cellTowerAddress":"","tempC":14.315109252929688,"humidity":77.19879150390625,"pressure":99504.5234375,"pM25":4.679520130157471,"pM10":6.921943664550781,"pM1":2.7161388397216797,"vBattery":4.165937423706055,"cellSignal":-99,"fwVersion":"","aqi":19,"aqiLabel":"Good","calibratedPM25":4.679520130157471,"calibrationVersion":"None"},{"deploymentName":"Tacoma","deviceFriendlyName":"Crescent Heights Elementary School","msrDeviceNbr":"2189","readingDateTimeUTC":"2022-05-28 14:55:57","readingDateTimeLocal":"2022-05-28 07:55:57","latitude":47.29472222,"longitude":-122.4,"cellTowerAddress":"","tempC":13.046722412109375,"humidity":77.5665283203125,"pressure":99535.3515625,"pM25":2.821704149246216,"pM10":2.821702241897583,"pM1":2.6683740615844727,"vBattery":4.167655944824219,"cellSignal":-99,"fwVersion":"","aqi":11,"aqiLabel":"Good","calibratedPM25":2.821704149246216,"calibrationVersion":"None"},{"deploymentName":"Tacoma","deviceFriendlyName":"Crescent Heights Elementary School","msrDeviceNbr":"2189","readingDateTimeUTC":"2022-05-28 14:35:46","readingDateTimeLocal":"2022-05-28 07:35:46","latitude":47.29472222,"longitude":-122.4,"cellTowerAddress":"","tempC":12.819747924804688,"humidity":77.691650390625,"pressure":99536.5859375,"pM25":1.3797248601913452,"pM10":1.3797239065170288,"pM1":1.3047512769699097,"vBattery":4.164843559265137,"cellSignal":-99,"fwVersion":"","aqi":5,"aqiLabel":"Good","calibratedPM25":1.3797248601913452,"calibrationVersion":"None"},{"deploymentName":"Tacoma","deviceFriendlyName":"Crescent Heights Elementary School","msrDeviceNbr":"2189","readingDateTimeUTC":"2022-05-28 14:15:35","readingDateTimeLocal":"2022-05-28 07:15:35","latitude":47.29472222,"longitude":-122.4,"cellTowerAddress":"","tempC":12.851791381835938,"humidity":75.82244873046875,"pressure":99546.7265625,"pM25":3.3044753074645996,"pM10":4.109691619873047,"pM1":2.511201858520508,"vBattery":4.165468692779541,"cellSignal":-100,"fwVersion":"","aqi":13,"aqiLabel":"Good","calibratedPM25":3.3044753074645996,"calibrationVersion":"None"},{"deploymentName":"Tacoma","deviceFriendlyName":"Crescent Heights Elementary School","msrDeviceNbr":"2189","readingDateTimeUTC":"2022-05-28 13:55:24","readingDateTimeLocal":"2022-05-28 06:55:24","latitude":47.29472222,"longitude":-122.4,"cellTowerAddress":"","tempC":12.79571533203125,"humidity":75.48828125,"pressure":99570.234375,"pM25":2.3760581016540527,"pM10":3.4074296951293945,"pM1":1.4608666896820068,"vBattery":4.163906097412109,"cellSignal":-101,"fwVersion":"","aqi":9,"aqiLabel":"Good","calibratedPM25":2.3760581016540527,"calibrationVersion":"None"},{"deploymentName":"Tacoma","deviceFriendlyName":"Crescent Heights Elementary School","msrDeviceNbr":"2189","readingDateTimeUTC":"2022-05-28 13:35:12","readingDateTimeLocal":"2022-05-28 06:35:12","latitude":47.29472222,"longitude":-122.4,"cellTowerAddress":"","tempC":12.53936767578125,"humidity":76.24053955078125,"pressure":99563.0078125,"pM25":1.3875253200531006,"pM10":1.3875243663787842,"pM1":1.3121278285980225,"vBattery":4.1640625,"cellSignal":-101,"fwVersion":"","aqi":5,"aqiLabel":"Good","calibratedPM25":1.3875253200531006,"calibrationVersion":"None"},{"deploymentName":"Tacoma","deviceFriendlyName":"Crescent Heights Elementary School","msrDeviceNbr":"2189","readingDateTimeUTC":"2022-05-28 13:15:01","readingDateTimeLocal":"2022-05-28 06:15:01","latitude":47.29472222,"longitude":-122.4,"cellTowerAddress":"","tempC":12.416534423828125,"humidity":76.77154541015625,"pressure":99598.2421875,"pM25":2.1252834796905518,"pM10":2.125282049179077,"pM1":2.009796619415283,"vBattery":4.164843559265137,"cellSignal":-101,"fwVersion":"","aqi":8,"aqiLabel":"Good","calibratedPM25":2.1252834796905518,"calibrationVersion":"None"},{"deploymentName":"Tacoma","deviceFriendlyName":"Crescent Heights Elementary School","msrDeviceNbr":"2189","readingDateTimeUTC":"2022-05-28 12:54:50","readingDateTimeLocal":"2022-05-28 05:54:50","latitude":47.29472222,"longitude":-122.4,"cellTowerAddress":"","tempC":12.04803466796875,"humidity":77.11029052734375,"pressure":99619.1328125,"pM25":1.3361656665802002,"pM10":1.3361647129058838,"pM1":1.2635589838027954,"vBattery":4.1640625,"cellSignal":-101,"fwVersion":"","aqi":5,"aqiLabel":"Good","calibratedPM25":1.3361656665802002,"calibrationVersion":"None"},{"deploymentName":"Tacoma","deviceFriendlyName":"Crescent Heights Elementary School","msrDeviceNbr":"2189","readingDateTimeUTC":"2022-05-28 12:34:39","readingDateTimeLocal":"2022-05-28 05:34:39","latitude":47.29472222,"longitude":-122.4,"cellTowerAddress":"","tempC":11.957244873046875,"humidity":76.5106201171875,"pressure":99624.984375,"pM25":2.362901210784912,"pM10":3.2145493030548096,"pM1":1.5854051113128662,"vBattery":4.164531230926514,"cellSignal":-101,"fwVersion":"","aqi":9,"aqiLabel":"Good","calibratedPM25":2.362901210784912,"calibrationVersion":"None"},{"deploymentName":"Tacoma","deviceFriendlyName":"Crescent Heights Elementary School","msrDeviceNbr":"2189","readingDateTimeUTC":"2022-05-28 12:14:28","readingDateTimeLocal":"2022-05-28 05:14:28","latitude":47.29472222,"longitude":-122.4,"cellTowerAddress":"","tempC":12.04803466796875,"humidity":77.569580078125,"pressure":99649.2890625,"pM25":3.6144638061523438,"pM10":3.7326977252960205,"pM1":3.3279383182525635,"vBattery":4.163906097412109,"cellSignal":-101,"fwVersion":"","aqi":15,"aqiLabel":"Good","calibratedPM25":3.6144638061523438,"calibrationVersion":"None"}]