[{"deploymentName":"Tacoma","deviceFriendlyName":"Crescent Heights Elementary School","msrDeviceNbr":"2189","readingDateTimeUTC":"2022-05-18 15:55:43","readingDateTimeLocal":"2022-05-18 08:55:43","latitude":47.29472222,"longitude":-122.4,"cellTowerAddress":"","tempC":11.6741943359375,"humidity":76.4404296875,"pressure":100009.328125,"pM25":1.916094422340393,"pM10":1.9160932302474976,"pM1":1.8119747638702393,"vBattery":4.174999713897705,"cellSignal":-103,"fwVersion":"","aqi":7,"aqiLabel":"Good","calibratedPM25":1.916094422340393,"calibrationVersion":"None"},{"deploymentName":"Tacoma","deviceFriendlyName":"Crescent Heights Elementary School","msrDeviceNbr":"2189","readingDateTimeUTC":"2022-05-18 15:35:32","readingDateTimeLocal":"2022-05-18 08:35:32","latitude":47.29472222,"longitude":-122.4,"cellTowerAddress":"","tempC":10.865097045898438,"humidity":80.55572509765625,"pressure":100002.15625,"pM25":5.029731750488281,"pM10":8.922761917114258,"pM1":1.7892849445343018,"vBattery":4.172812461853027,"cellSignal":-100,"fwVersion":"","aqi":20,"aqiLabel":"Good","calibratedPM25":5.029731750488281,"calibrationVersion":"None"},{"deploymentName":"Tacoma","deviceFriendlyName":"Crescent Heights Elementary School","msrDeviceNbr":"2189","readingDateTimeUTC":"2022-05-18 15:15:21","readingDateTimeLocal":"2022-05-18 08:15:21","latitude":47.29472222,"longitude":-122.4,"cellTowerAddress":"","tempC":10.08270263671875,"humidity":83.3831787109375,"pressure":99987.6796875,"pM25":0.7163479328155518,"pM10":0.7163474559783936,"pM1":0.6774219274520874,"vBattery":4.171562194824219,"cellSignal":-100,"fwVersion":"","aqi":2,"aqiLabel":"Good","calibratedPM25":0.7163479328155518,"calibrationVersion":"None"},{"deploymentName":"Tacoma","deviceFriendlyName":"Crescent Heights Elementary School","msrDeviceNbr":"2189","readingDateTimeUTC":"2022-05-18 14:55:09","readingDateTimeLocal":"2022-05-18 07:55:09","latitude":47.29472222,"longitude":-122.4,"cellTowerAddress":"","tempC":9.778289794921875,"humidity":84.942626953125,"pressure":99987.6328125,"pM25":1.5323480367660522,"pM10":1.5323469638824463,"pM1":1.4490809440612793,"vBattery":4.169687271118164,"cellSignal":-101,"fwVersion":"","aqi":6,"aqiLabel":"Good","calibratedPM25":1.5323480367660522,"calibrationVersion":"None"},{"deploymentName":"Tacoma","deviceFriendlyName":"Crescent Heights Elementary School","msrDeviceNbr":"2189","readingDateTimeUTC":"2022-05-18 14:34:57","readingDateTimeLocal":"2022-05-18 07:34:57","latitude":47.29472222,"longitude":-122.4,"cellTowerAddress":"","tempC":9.425811767578125,"humidity":85.06622314453125,"pressure":99989.8046875,"pM25":1.7505820989608765,"pM10":2.6632885932922363,"pM1":0.9598221778869629,"vBattery":4.166093826293945,"cellSignal":-100,"fwVersion":"","aqi":7,"aqiLabel":"Good","calibratedPM25":1.7505820989608765,"calibrationVersion":"None"},{"deploymentName":"Tacoma","deviceFriendlyName":"Crescent Heights Elementary School","msrDeviceNbr":"2189","readingDateTimeUTC":"2022-05-18 14:14:45","readingDateTimeLocal":"2022-05-18 07:14:45","latitude":47.29472222,"longitude":-122.4,"cellTowerAddress":"","tempC":9.214859008789062,"humidity":85.70098876953125,"pressure":100008.796875,"pM25":4.260280132293701,"pM10":6.5264458656311035,"pM1":2.301583766937256,"vBattery":4.165468692779541,"cellSignal":-99,"fwVersion":"","aqi":17,"aqiLabel":"Good","calibratedPM25":4.260280132293701,"calibrationVersion":"None"},{"deploymentName":"Tacoma","deviceFriendlyName":"Crescent Heights Elementary School","msrDeviceNbr":"2189","readingDateTimeUTC":"2022-05-18 13:54:33","readingDateTimeLocal":"2022-05-18 06:54:33","latitude":47.29472222,"longitude":-122.4,"cellTowerAddress":"","tempC":9.059982299804688,"humidity":86.46697998046875,"pressure":100006.4453125,"pM25":10.304431915283203,"pM10":15.337188720703125,"pM1":5.908695220947266,"vBattery":4.164531230926514,"cellSignal":-98,"fwVersion":"","aqi":42,"aqiLabel":"Good","calibratedPM25":10.304431915283203,"calibrationVersion":"None"},{"deploymentName":"Tacoma","deviceFriendlyName":"Crescent Heights Elementary School","msrDeviceNbr":"2189","readingDateTimeUTC":"2022-05-18 13:34:21","readingDateTimeLocal":"2022-05-18 06:34:21","latitude":47.29472222,"longitude":-122.4,"cellTowerAddress":"","tempC":8.8330078125,"humidity":85.58197021484375,"pressure":100022.109375,"pM25":5.5125956535339355,"pM10":5.51259183883667,"pM1":5.213043689727783,"vBattery":4.165937423706055,"cellSignal":-99,"fwVersion":"","aqi":22,"aqiLabel":"Good","calibratedPM25":5.5125956535339355,"calibrationVersion":"None"},{"deploymentName":"Tacoma","deviceFriendlyName":"Crescent Heights Elementary School","msrDeviceNbr":"2189","readingDateTimeUTC":"2022-05-18 13:14:09","readingDateTimeLocal":"2022-05-18 06:14:09","latitude":47.29472222,"longitude":-122.4,"cellTowerAddress":"","tempC":8.8116455078125,"humidity":84.8602294921875,"pressure":100040.171875,"pM25":4.592496871948242,"pM10":5.901970863342285,"pM1":3.3449056148529053,"vBattery":4.165781021118164,"cellSignal":-99,"fwVersion":"","aqi":19,"aqiLabel":"Good","calibratedPM25":4.592496871948242,"calibrationVersion":"None"},{"deploymentName":"Tacoma","deviceFriendlyName":"Crescent Heights Elementary School","msrDeviceNbr":"2189","readingDateTimeUTC":"2022-05-18 12:53:57","readingDateTimeLocal":"2022-05-18 05:53:57","latitude":47.29472222,"longitude":-122.4,"cellTowerAddress":"","tempC":8.86505126953125,"humidity":83.09783935546875,"pressure":100116.796875,"pM25":7.028076171875,"pM10":8.47344970703125,"pM1":5.544558048248291,"vBattery":4.164843559265137,"cellSignal":-98,"fwVersion":"","aqi":29,"aqiLabel":"Good","calibratedPM25":7.028076171875,"calibrationVersion":"None"},{"deploymentName":"Tacoma","deviceFriendlyName":"Crescent Heights Elementary School","msrDeviceNbr":"2189","readingDateTimeUTC":"2022-05-18 12:33:46","readingDateTimeLocal":"2022-05-18 05:33:46","latitude":47.29472222,"longitude":-122.4,"cellTowerAddress":"","tempC":9.0679931640625,"humidity":81.34002685546875,"pressure":100168.7265625,"pM25":9.582316398620605,"pM10":9.58230972290039,"pM1":9.061617851257324,"vBattery":4.166249752044678,"cellSignal":-99,"fwVersion":"","aqi":39,"aqiLabel":"Good","calibratedPM25":9.582316398620605,"calibrationVersion":"None"},{"deploymentName":"Tacoma","deviceFriendlyName":"Crescent Heights Elementary School","msrDeviceNbr":"2189","readingDateTimeUTC":"2022-05-18 12:13:34","readingDateTimeLocal":"2022-05-18 05:13:34","latitude":47.29472222,"longitude":-122.4,"cellTowerAddress":"","tempC":9.433822631835938,"humidity":79.3060302734375,"pressure":100211.5859375,"pM25":5.008909702301025,"pM10":6.845337390899658,"pM1":3.3370625972747803,"vBattery":4.165468692779541,"cellSignal":-98,"fwVersion":"","aqi":20,"aqiLabel":"Good","calibratedPM25":5.008909702301025,"calibrationVersion":"None"},{"deploymentName":"Tacoma","deviceFriendlyName":"Crescent Heights Elementary School","msrDeviceNbr":"2189","readingDateTimeUTC":"2022-05-18 11:53:23","readingDateTimeLocal":"2022-05-18 04:53:23","latitude":47.29472222,"longitude":-122.4,"cellTowerAddress":"","tempC":9.551315307617188,"humidity":78.3203125,"pressure":100216.171875,"pM25":11.292990684509277,"pM10":16.78349494934082,"pM1":6.494659900665283,"vBattery":4.161718845367432,"cellSignal":-97,"fwVersion":"","aqi":47,"aqiLabel":"Good","calibratedPM25":11.292990684509277,"calibrationVersion":"None"},{"deploymentName":"Tacoma","deviceFriendlyName":"Crescent Heights Elementary School","msrDeviceNbr":"2189","readingDateTimeUTC":"2022-05-18 11:33:11","readingDateTimeLocal":"2022-05-18 04:33:11","latitude":47.29472222,"longitude":-122.4,"cellTowerAddress":"","tempC":9.778289794921875,"humidity":77.1148681640625,"pressure":100257.84375,"pM25":4.7419233322143555,"pM10":4.741919994354248,"pM1":4.484249114990234,"vBattery":4.166249752044678,"cellSignal":-98,"fwVersion":"","aqi":19,"aqiLabel":"Good","calibratedPM25":4.7419233322143555,"calibrationVersion":"None"},{"deploymentName":"Tacoma","deviceFriendlyName":"Crescent Heights Elementary School","msrDeviceNbr":"2189","readingDateTimeUTC":"2022-05-18 11:13:00","readingDateTimeLocal":"2022-05-18 04:13:00","latitude":47.29472222,"longitude":-122.4,"cellTowerAddress":"","tempC":9.746246337890625,"humidity":76.00250244140625,"pressure":100215.1171875,"pM25":6.328157901763916,"pM10":8.286149024963379,"pM1":4.491973876953125,"vBattery":4.166718482971191,"cellSignal":-97,"fwVersion":"","aqi":26,"aqiLabel":"Good","calibratedPM25":6.328157901763916,"calibrationVersion":"None"},{"deploymentName":"Tacoma","deviceFriendlyName":"Crescent Heights Elementary School","msrDeviceNbr":"2189","readingDateTimeUTC":"2022-05-18 10:52:48","readingDateTimeLocal":"2022-05-18 03:52:48","latitude":47.29472222,"longitude":-122.4,"cellTowerAddress":"","tempC":10.3070068359375,"humidity":72.16796875,"pressure":100271.3125,"pM25":4.467055797576904,"pM10":5.5319905281066895,"pM1":3.412660837173462,"vBattery":4.166718482971191,"cellSignal":-97,"fwVersion":"","aqi":18,"aqiLabel":"Good","calibratedPM25":4.467055797576904,"calibrationVersion":"None"},{"deploymentName":"Tacoma","deviceFriendlyName":"Crescent Heights Elementary School","msrDeviceNbr":"2189","readingDateTimeUTC":"2022-05-18 10:32:37","readingDateTimeLocal":"2022-05-18 03:32:37","latitude":47.29472222,"longitude":-122.4,"cellTowerAddress":"","tempC":10.803680419921875,"humidity":69.8333740234375,"pressure":100280.9296875,"pM25":7.1633100509643555,"pM10":7.163305282592773,"pM1":6.774059295654297,"vBattery":4.168281078338623,"cellSignal":-98,"fwVersion":"","aqi":29,"aqiLabel":"Good","calibratedPM25":7.1633100509643555,"calibrationVersion":"None"},{"deploymentName":"Tacoma","deviceFriendlyName":"Crescent Heights Elementary School","msrDeviceNbr":"2189","readingDateTimeUTC":"2022-05-18 10:12:25","readingDateTimeLocal":"2022-05-18 03:12:25","latitude":47.29472222,"longitude":-122.4,"cellTowerAddress":"","tempC":11.270980834960938,"humidity":66.68243408203125,"pressure":100348.0546875,"pM25":3.542722225189209,"pM10":3.542719841003418,"pM1":3.350212335586548,"vBattery":4.167031288146973,"cellSignal":-98,"fwVersion":"","aqi":14,"aqiLabel":"Good","calibratedPM25":3.542722225189209,"calibrationVersion":"None"},{"deploymentName":"Tacoma","deviceFriendlyName":"Crescent Heights Elementary School","msrDeviceNbr":"2189","readingDateTimeUTC":"2022-05-18 09:52:13","readingDateTimeLocal":"2022-05-18 02:52:13","latitude":47.29472222,"longitude":-122.4,"cellTowerAddress":"","tempC":11.794357299804688,"humidity":64.84222412109375,"pressure":100391.7734375,"pM25":6.607185363769531,"pM10":10.02688980102539,"pM1":3.6417715549468994,"vBattery":4.167812347412109,"cellSignal":-99,"fwVersion":"","aqi":27,"aqiLabel":"Good","calibratedPM25":6.607185363769531,"calibrationVersion":"None"},{"deploymentName":"Tacoma","deviceFriendlyName":"Crescent Heights Elementary School","msrDeviceNbr":"2189","readingDateTimeUTC":"2022-05-18 09:32:01","readingDateTimeLocal":"2022-05-18 02:32:01","latitude":47.29472222,"longitude":-122.4,"cellTowerAddress":"","tempC":12.056045532226562,"humidity":63.17901611328125,"pressure":100303.15625,"pM25":6.089467525482178,"pM10":7.383070945739746,"pM1":4.772624969482422,"vBattery":4.166718482971191,"cellSignal":-100,"fwVersion":"","aqi":25,"aqiLabel":"Good","calibratedPM25":6.089467525482178,"calibrationVersion":"None"},{"deploymentName":"Tacoma","deviceFriendlyName":"Crescent Heights Elementary School","msrDeviceNbr":"2189","readingDateTimeUTC":"2022-05-18 09:11:50","readingDateTimeLocal":"2022-05-18 02:11:50","latitude":47.29472222,"longitude":-122.4,"cellTowerAddress":"","tempC":12.291030883789062,"humidity":59.9517822265625,"pressure":100331.7890625,"pM25":5.578336715698242,"pM10":7.119045257568359,"pM1":4.100935459136963,"vBattery":4.168749809265137,"cellSignal":-100,"fwVersion":"","aqi":23,"aqiLabel":"Good","calibratedPM25":5.578336715698242,"calibrationVersion":"None"},{"deploymentName":"Tacoma","deviceFriendlyName":"Crescent Heights Elementary School","msrDeviceNbr":"2189","readingDateTimeUTC":"2022-05-18 08:51:39","readingDateTimeLocal":"2022-05-18 01:51:39","latitude":47.29472222,"longitude":-122.4,"cellTowerAddress":"","tempC":12.696914672851562,"humidity":58.2611083984375,"pressure":100367.703125,"pM25":3.460141897201538,"pM10":3.460139513015747,"pM1":3.2721195220947266,"vBattery":4.16796875,"cellSignal":-100,"fwVersion":"","aqi":14,"aqiLabel":"Good","calibratedPM25":3.460141897201538,"calibrationVersion":"None"},{"deploymentName":"Tacoma","deviceFriendlyName":"Crescent Heights Elementary School","msrDeviceNbr":"2189","readingDateTimeUTC":"2022-05-18 08:31:27","readingDateTimeLocal":"2022-05-18 01:31:27","latitude":47.29472222,"longitude":-122.4,"cellTowerAddress":"","tempC":12.782363891601562,"humidity":57.37762451171875,"pressure":100451.2734375,"pM25":2.0604963302612305,"pM10":2.6064436435699463,"pM1":1.5324265956878662,"vBattery":4.169062614440918,"cellSignal":-100,"fwVersion":"","aqi":8,"aqiLabel":"Good","calibratedPM25":2.0604963302612305,"calibrationVersion":"None"},{"deploymentName":"Tacoma","deviceFriendlyName":"Crescent Heights Elementary School","msrDeviceNbr":"2189","readingDateTimeUTC":"2022-05-18 08:11:15","readingDateTimeLocal":"2022-05-18 01:11:15","latitude":47.29472222,"longitude":-122.4,"cellTowerAddress":"","tempC":12.803726196289062,"humidity":55.9112548828125,"pressure":100477.9140625,"pM25":1.8811568021774292,"pM10":2.2361111640930176,"pM1":1.5084013938903809,"vBattery":4.170156002044678,"cellSignal":-99,"fwVersion":"","aqi":7,"aqiLabel":"Good","calibratedPM25":1.8811568021774292,"calibrationVersion":"None"},{"deploymentName":"Tacoma","deviceFriendlyName":"Crescent Heights Elementary School","msrDeviceNbr":"2189","readingDateTimeUTC":"2022-05-18 07:51:03","readingDateTimeLocal":"2022-05-18 00:51:03","latitude":47.29472222,"longitude":-122.4,"cellTowerAddress":"","tempC":13.1695556640625,"humidity":54.400634765625,"pressure":100483.9375,"pM25":1.1874277591705322,"pM10":1.187427043914795,"pM1":1.12290358543396,"vBattery":4.168906211853027,"cellSignal":-100,"fwVersion":"","aqi":4,"aqiLabel":"Good","calibratedPM25":1.1874277591705322,"calibrationVersion":"None"},{"deploymentName":"Tacoma","deviceFriendlyName":"Crescent Heights Elementary School","msrDeviceNbr":"2189","readingDateTimeUTC":"2022-05-18 07:30:52","readingDateTimeLocal":"2022-05-18 00:30:52","latitude":47.29472222,"longitude":-122.4,"cellTowerAddress":"","tempC":13.316421508789062,"humidity":53.424072265625,"pressure":100518.4921875,"pM25":2.0819292068481445,"pM10":2.08192777633667,"pM1":1.968798041343689,"vBattery":4.170156002044678,"cellSignal":-100,"fwVersion":"","aqi":8,"aqiLabel":"Good","calibratedPM25":2.0819292068481445,"calibrationVersion":"None"},{"deploymentName":"Tacoma","deviceFriendlyName":"Crescent Heights Elementary School","msrDeviceNbr":"2189","readingDateTimeUTC":"2022-05-18 07:10:40","readingDateTimeLocal":"2022-05-18 00:10:40","latitude":47.29472222,"longitude":-122.4,"cellTowerAddress":"","tempC":13.668899536132812,"humidity":53.22113037109375,"pressure":100542.9453125,"pM25":2.00663423538208,"pM10":2.5440456867218018,"pM1":1.4879976511001587,"vBattery":4.169531345367432,"cellSignal":-100,"fwVersion":"","aqi":8,"aqiLabel":"Good","calibratedPM25":2.00663423538208,"calibrationVersion":"None"},{"deploymentName":"Tacoma","deviceFriendlyName":"Crescent Heights Elementary School","msrDeviceNbr":"2189","readingDateTimeUTC":"2022-05-18 06:50:29","readingDateTimeLocal":"2022-05-17 23:50:29","latitude":47.29472222,"longitude":-122.4,"cellTowerAddress":"","tempC":13.783721923828125,"humidity":52.80303955078125,"pressure":100570.8125,"pM25":1.266374945640564,"pM10":1.6208239793777466,"pM1":0.9274117350578308,"vBattery":4.169843673706055,"cellSignal":-100,"fwVersion":"","aqi":5,"aqiLabel":"Good","calibratedPM25":1.266374945640564,"calibrationVersion":"None"},{"deploymentName":"Tacoma","deviceFriendlyName":"Crescent Heights Elementary School","msrDeviceNbr":"2189","readingDateTimeUTC":"2022-05-18 06:30:17","readingDateTimeLocal":"2022-05-17 23:30:17","latitude":47.29472222,"longitude":-122.4,"cellTowerAddress":"","tempC":13.911895751953125,"humidity":51.6265869140625,"pressure":100589.9609375,"pM25":2.089071035385132,"pM10":2.0890696048736572,"pM1":1.975551962852478,"vBattery":4.170312404632568,"cellSignal":-100,"fwVersion":"","aqi":8,"aqiLabel":"Good","calibratedPM25":2.089071035385132,"calibrationVersion":"None"},{"deploymentName":"Tacoma","deviceFriendlyName":"Crescent Heights Elementary School","msrDeviceNbr":"2189","readingDateTimeUTC":"2022-05-18 06:10:06","readingDateTimeLocal":"2022-05-17 23:10:06","latitude":47.29472222,"longitude":-122.4,"cellTowerAddress":"","tempC":14.29107666015625,"humidity":50.115966796875,"pressure":100624.7421875,"pM25":4.7393903732299805,"pM10":6.179553508758545,"pM1":3.3842108249664307,"vBattery":4.170781135559082,"cellSignal":-100,"fwVersion":"","aqi":19,"aqiLabel":"Good","calibratedPM25":4.7393903732299805,"calibrationVersion":"None"},{"deploymentName":"Tacoma","deviceFriendlyName":"Crescent Heights Elementary School","msrDeviceNbr":"2189","readingDateTimeUTC":"2022-05-18 05:49:54","readingDateTimeLocal":"2022-05-17 22:49:54","latitude":47.29472222,"longitude":-122.4,"cellTowerAddress":"","tempC":14.758377075195312,"humidity":48.53363037109375,"pressure":100649.703125,"pM25":1.7239453792572021,"pM10":1.9958125352859497,"pM1":1.4230586290359497,"vBattery":4.171875,"cellSignal":-100,"fwVersion":"","aqi":7,"aqiLabel":"Good","calibratedPM25":1.7239453792572021,"calibrationVersion":"None"},{"deploymentName":"Tacoma","deviceFriendlyName":"Crescent Heights Elementary School","msrDeviceNbr":"2189","readingDateTimeUTC":"2022-05-18 05:29:42","readingDateTimeLocal":"2022-05-17 22:29:42","latitude":47.29472222,"longitude":-122.4,"cellTowerAddress":"","tempC":14.843826293945312,"humidity":47.61962890625,"pressure":100672.8203125,"pM25":5.894680023193359,"pM10":9.222768783569336,"pM1":3.037810802459717,"vBattery":4.170937538146973,"cellSignal":-100,"fwVersion":"","aqi":24,"aqiLabel":"Good","calibratedPM25":5.894680023193359,"calibrationVersion":"None"},{"deploymentName":"Tacoma","deviceFriendlyName":"Crescent Heights Elementary School","msrDeviceNbr":"2189","readingDateTimeUTC":"2022-05-18 05:09:31","readingDateTimeLocal":"2022-05-17 22:09:31","latitude":47.29472222,"longitude":-122.4,"cellTowerAddress":"","tempC":15.287094116210938,"humidity":48.21929931640625,"pressure":100675.546875,"pM25":1.9097775220870972,"pM10":1.909776210784912,"pM1":1.80600106716156,"vBattery":4.171562194824219,"cellSignal":-100,"fwVersion":"","aqi":7,"aqiLabel":"Good","calibratedPM25":1.9097775220870972,"calibrationVersion":"None"},{"deploymentName":"Tacoma","deviceFriendlyName":"Crescent Heights Elementary School","msrDeviceNbr":"2189","readingDateTimeUTC":"2022-05-18 04:49:19","readingDateTimeLocal":"2022-05-17 21:49:19","latitude":47.29472222,"longitude":-122.4,"cellTowerAddress":"","tempC":15.287094116210938,"humidity":48.32916259765625,"pressure":100689.3046875,"pM25":4.477797508239746,"pM10":4.477794170379639,"pM1":4.234476089477539,"vBattery":4.172656059265137,"cellSignal":-100,"fwVersion":"","aqi":18,"aqiLabel":"Good","calibratedPM25":4.477797508239746,"calibrationVersion":"None"},{"deploymentName":"Tacoma","deviceFriendlyName":"Crescent Heights Elementary School","msrDeviceNbr":"2189","readingDateTimeUTC":"2022-05-18 04:29:06","readingDateTimeLocal":"2022-05-17 21:29:06","latitude":47.29472222,"longitude":-122.4,"cellTowerAddress":"","tempC":15.287094116210938,"humidity":48.92120361328125,"pressure":100692.640625,"pM25":1.4230133295059204,"pM10":1.423012375831604,"pM1":1.3456873893737793,"vBattery":4.173749923706055,"cellSignal":-100,"fwVersion":"","aqi":5,"aqiLabel":"Good","calibratedPM25":1.4230133295059204,"calibrationVersion":"None"},{"deploymentName":"Tacoma","deviceFriendlyName":"Crescent Heights Elementary School","msrDeviceNbr":"2189","readingDateTimeUTC":"2022-05-18 04:08:54","readingDateTimeLocal":"2022-05-17 21:08:54","latitude":47.29472222,"longitude":-122.4,"cellTowerAddress":"","tempC":15.404586791992188,"humidity":48.370361328125,"pressure":100697.1640625,"pM25":1.2669360637664795,"pM10":1.7110356092453003,"pM1":0.8596141934394836,"vBattery":4.171562194824219,"cellSignal":-100,"fwVersion":"","aqi":5,"aqiLabel":"Good","calibratedPM25":1.2669360637664795,"calibrationVersion":"None"},{"deploymentName":"Tacoma","deviceFriendlyName":"Crescent Heights Elementary School","msrDeviceNbr":"2189","readingDateTimeUTC":"2022-05-18 03:48:42","readingDateTimeLocal":"2022-05-17 20:48:42","latitude":47.29472222,"longitude":-122.4,"cellTowerAddress":"","tempC":15.901260375976562,"humidity":48.32916259765625,"pressure":100718.3203125,"pM25":1.9821127653121948,"pM10":1.9821113348007202,"pM1":1.8744056224822998,"vBattery":4.173749923706055,"cellSignal":-100,"fwVersion":"","aqi":8,"aqiLabel":"Good","calibratedPM25":1.9821127653121948,"calibrationVersion":"None"},{"deploymentName":"Tacoma","deviceFriendlyName":"Crescent Heights Elementary School","msrDeviceNbr":"2189","readingDateTimeUTC":"2022-05-18 03:28:30","readingDateTimeLocal":"2022-05-17 20:28:30","latitude":47.29472222,"longitude":-122.4,"cellTowerAddress":"","tempC":16.47003173828125,"humidity":48.3306884765625,"pressure":100742.125,"pM25":2.640026807785034,"pM10":3.9132189750671387,"pM1":1.5261855125427246,"vBattery":4.173281192779541,"cellSignal":-100,"fwVersion":"","aqi":11,"aqiLabel":"Good","calibratedPM25":2.640026807785034,"calibrationVersion":"None"},{"deploymentName":"Tacoma","deviceFriendlyName":"Crescent Heights Elementary School","msrDeviceNbr":"2189","readingDateTimeUTC":"2022-05-18 03:08:18","readingDateTimeLocal":"2022-05-17 20:08:18","latitude":47.29472222,"longitude":-122.4,"cellTowerAddress":"","tempC":16.803817749023438,"humidity":46.783447265625,"pressure":100749.75,"pM25":2.4767847061157227,"pM10":3.5634355545043945,"pM1":1.5139880180358887,"vBattery":4.173906326293945,"cellSignal":-100,"fwVersion":"","aqi":10,"aqiLabel":"Good","calibratedPM25":2.4767847061157227,"calibrationVersion":"None"},{"deploymentName":"Tacoma","deviceFriendlyName":"Crescent Heights Elementary School","msrDeviceNbr":"2189","readingDateTimeUTC":"2022-05-18 02:48:07","readingDateTimeLocal":"2022-05-17 19:48:07","latitude":47.29472222,"longitude":-122.4,"cellTowerAddress":"","tempC":17.15362548828125,"humidity":46.08001708984375,"pressure":100766.1015625,"pM25":5.072844505310059,"pM10":8.167141914367676,"pM1":2.438821315765381,"vBattery":4.175937175750732,"cellSignal":-100,"fwVersion":"","aqi":21,"aqiLabel":"Good","calibratedPM25":5.072844505310059,"calibrationVersion":"None"},{"deploymentName":"Tacoma","deviceFriendlyName":"Crescent Heights Elementary School","msrDeviceNbr":"2189","readingDateTimeUTC":"2022-05-18 02:27:52","readingDateTimeLocal":"2022-05-17 19:27:52","latitude":47.29472222,"longitude":-122.4,"cellTowerAddress":"","tempC":17.177658081054688,"humidity":46.29364013671875,"pressure":100795.9375,"pM25":2.041193962097168,"pM10":2.0411925315856934,"pM1":1.9302765130996704,"vBattery":4.174999713897705,"cellSignal":-101,"fwVersion":"","aqi":8,"aqiLabel":"Good","calibratedPM25":2.041193962097168,"calibrationVersion":"None"},{"deploymentName":"Tacoma","deviceFriendlyName":"Crescent Heights Elementary School","msrDeviceNbr":"2189","readingDateTimeUTC":"2022-05-18 02:07:40","readingDateTimeLocal":"2022-05-17 19:07:40","latitude":47.29472222,"longitude":-122.4,"cellTowerAddress":"","tempC":17.30316162109375,"humidity":46.11053466796875,"pressure":100786.8203125,"pM25":5.0922346115112305,"pM10":7.798047065734863,"pM1":2.753248691558838,"vBattery":4.174687385559082,"cellSignal":-100,"fwVersion":"","aqi":21,"aqiLabel":"Good","calibratedPM25":5.0922346115112305,"calibrationVersion":"None"},{"deploymentName":"Tacoma","deviceFriendlyName":"Crescent Heights Elementary School","msrDeviceNbr":"2189","readingDateTimeUTC":"2022-05-18 01:47:29","readingDateTimeLocal":"2022-05-17 18:47:29","latitude":47.29472222,"longitude":-122.4,"cellTowerAddress":"","tempC":17.620925903320312,"humidity":45.7855224609375,"pressure":100828.3671875,"pM25":3.3950963020324707,"pM10":4.243309020996094,"pM1":2.564129590988159,"vBattery":4.175624847412109,"cellSignal":-100,"fwVersion":"","aqi":14,"aqiLabel":"Good","calibratedPM25":3.3950963020324707,"calibrationVersion":"None"},{"deploymentName":"Tacoma","deviceFriendlyName":"Crescent Heights Elementary School","msrDeviceNbr":"2189","readingDateTimeUTC":"2022-05-18 01:27:17","readingDateTimeLocal":"2022-05-17 18:27:17","latitude":47.29472222,"longitude":-122.4,"cellTowerAddress":"","tempC":17.289810180664062,"humidity":45.2667236328125,"pressure":100854.0234375,"pM25":2.9248287677764893,"pM10":4.573322296142578,"pM1":1.5094695091247559,"vBattery":4.172030925750732,"cellSignal":-100,"fwVersion":"","aqi":12,"aqiLabel":"Good","calibratedPM25":2.9248287677764893,"calibrationVersion":"None"},{"deploymentName":"Tacoma","deviceFriendlyName":"Crescent Heights Elementary School","msrDeviceNbr":"2189","readingDateTimeUTC":"2022-05-18 01:07:05","readingDateTimeLocal":"2022-05-17 18:07:05","latitude":47.29472222,"longitude":-122.4,"cellTowerAddress":"","tempC":17.717056274414062,"humidity":45.17822265625,"pressure":100868.3984375,"pM25":2.0238592624664307,"pM10":2.023857831954956,"pM1":1.9138836860656738,"vBattery":4.174375057220459,"cellSignal":-100,"fwVersion":"","aqi":8,"aqiLabel":"Good","calibratedPM25":2.0238592624664307,"calibrationVersion":"None"},{"deploymentName":"Tacoma","deviceFriendlyName":"Crescent Heights Elementary School","msrDeviceNbr":"2189","readingDateTimeUTC":"2022-05-18 00:46:53","readingDateTimeLocal":"2022-05-17 17:46:53","latitude":47.29472222,"longitude":-122.4,"cellTowerAddress":"","tempC":18.152313232421875,"humidity":44.1650390625,"pressure":100906.2734375,"pM25":0.7787799835205078,"pM10":0.7787795066833496,"pM1":0.7364614605903625,"vBattery":4.174843788146973,"cellSignal":-100,"fwVersion":"","aqi":3,"aqiLabel":"Good","calibratedPM25":0.7787799835205078,"calibrationVersion":"None"},{"deploymentName":"Tacoma","deviceFriendlyName":"Crescent Heights Elementary School","msrDeviceNbr":"2189","readingDateTimeUTC":"2022-05-18 00:26:41","readingDateTimeLocal":"2022-05-17 17:26:41","latitude":47.29472222,"longitude":-122.4,"cellTowerAddress":"","tempC":18.64898681640625,"humidity":43.511962890625,"pressure":100923.90625,"pM25":0.76199871301651,"pM10":0.761998176574707,"pM1":0.7205920815467834,"vBattery":4.172343730926514,"cellSignal":-100,"fwVersion":"","aqi":3,"aqiLabel":"Good","calibratedPM25":0.76199871301651,"calibrationVersion":"None"},{"deploymentName":"Tacoma","deviceFriendlyName":"Crescent Heights Elementary School","msrDeviceNbr":"2189","readingDateTimeUTC":"2022-05-18 00:06:29","readingDateTimeLocal":"2022-05-17 17:06:29","latitude":47.29472222,"longitude":-122.4,"cellTowerAddress":"","tempC":19.148330688476562,"humidity":41.50238037109375,"pressure":100945.2734375,"pM25":12.284798622131348,"pM10":20.967241287231445,"pM1":4.999788761138916,"vBattery":4.172187328338623,"cellSignal":-100,"fwVersion":"","aqi":52,"aqiLabel":"Moderate","calibratedPM25":12.284798622131348,"calibrationVersion":"None"},{"deploymentName":"Tacoma","deviceFriendlyName":"Crescent Heights Elementary School","msrDeviceNbr":"2189","readingDateTimeUTC":"2022-05-17 23:46:18","readingDateTimeLocal":"2022-05-17 16:46:18","latitude":47.29472222,"longitude":-122.4,"cellTowerAddress":"","tempC":19.989471435546875,"humidity":40.46173095703125,"pressure":100953.796875,"pM25":2.674271583557129,"pM10":2.674269914627075,"pM1":2.5289530754089355,"vBattery":4.171718597412109,"cellSignal":-100,"fwVersion":"","aqi":11,"aqiLabel":"Good","calibratedPM25":2.674271583557129,"calibrationVersion":"None"},{"deploymentName":"Tacoma","deviceFriendlyName":"Crescent Heights Elementary School","msrDeviceNbr":"2189","readingDateTimeUTC":"2022-05-17 23:26:06","readingDateTimeLocal":"2022-05-17 16:26:06","latitude":47.29472222,"longitude":-122.4,"cellTowerAddress":"","tempC":20.790557861328125,"humidity":39.45770263671875,"pressure":100958.390625,"pM25":1.7608097791671753,"pM10":2.8132803440093994,"pM1":0.8629716038703918,"vBattery":4.166718482971191,"cellSignal":-101,"fwVersion":"","aqi":7,"aqiLabel":"Good","calibratedPM25":1.7608097791671753,"calibrationVersion":"None"},{"deploymentName":"Tacoma","deviceFriendlyName":"Crescent Heights Elementary School","msrDeviceNbr":"2189","readingDateTimeUTC":"2022-05-17 23:05:54","readingDateTimeLocal":"2022-05-17 16:05:54","latitude":47.29472222,"longitude":-122.4,"cellTowerAddress":"","tempC":21.265869140625,"humidity":38.1439208984375,"pressure":100954.71875,"pM25":0.7260098457336426,"pM10":0.7260093688964844,"pM1":0.6865587830543518,"vBattery":4.165781021118164,"cellSignal":-101,"fwVersion":"","aqi":3,"aqiLabel":"Good","calibratedPM25":0.7260098457336426,"calibrationVersion":"None"},{"deploymentName":"Tacoma","deviceFriendlyName":"Crescent Heights Elementary School","msrDeviceNbr":"2189","readingDateTimeUTC":"2022-05-17 22:45:42","readingDateTimeLocal":"2022-05-17 15:45:42","latitude":47.29472222,"longitude":-122.4,"cellTowerAddress":"","tempC":22.128372192382812,"humidity":36.0137939453125,"pressure":100975.6640625,"pM25":2.535055637359619,"pM10":2.5350537300109863,"pM1":2.3973019123077393,"vBattery":4.157812595367432,"cellSignal":-100,"fwVersion":"","aqi":10,"aqiLabel":"Good","calibratedPM25":2.535055637359619,"calibrationVersion":"None"},{"deploymentName":"Tacoma","deviceFriendlyName":"Crescent Heights Elementary School","msrDeviceNbr":"2189","readingDateTimeUTC":"2022-05-17 22:25:30","readingDateTimeLocal":"2022-05-17 15:25:30","latitude":47.29472222,"longitude":-122.4,"cellTowerAddress":"","tempC":22.766571044921875,"humidity":35.24627685546875,"pressure":100973.09375,"pM25":1.1187800168991089,"pM10":1.494594931602478,"pM1":0.7715525031089783,"vBattery":4.164218425750732,"cellSignal":-101,"fwVersion":"","aqi":4,"aqiLabel":"Good","calibratedPM25":1.1187800168991089,"calibrationVersion":"None"},{"deploymentName":"Tacoma","deviceFriendlyName":"Crescent Heights Elementary School","msrDeviceNbr":"2189","readingDateTimeUTC":"2022-05-17 22:05:18","readingDateTimeLocal":"2022-05-17 15:05:18","latitude":47.29472222,"longitude":-122.4,"cellTowerAddress":"","tempC":23.75457763671875,"humidity":33.642578125,"pressure":100983.359375,"pM25":2.950340986251831,"pM10":4.5886616706848145,"pM1":1.5413501262664795,"vBattery":4.162187576293945,"cellSignal":-101,"fwVersion":"","aqi":12,"aqiLabel":"Good","calibratedPM25":2.950340986251831,"calibrationVersion":"None"},{"deploymentName":"Tacoma","deviceFriendlyName":"Crescent Heights Elementary School","msrDeviceNbr":"2189","readingDateTimeUTC":"2022-05-17 21:45:06","readingDateTimeLocal":"2022-05-17 14:45:06","latitude":47.29472222,"longitude":-122.4,"cellTowerAddress":"","tempC":24.026947021484375,"humidity":33.08563232421875,"pressure":100996.1953125,"pM25":2.6145970821380615,"pM10":3.743558645248413,"pM1":1.6120645999908447,"vBattery":4.161874771118164,"cellSignal":-101,"fwVersion":"","aqi":10,"aqiLabel":"Good","calibratedPM25":2.6145970821380615,"calibrationVersion":"None"},{"deploymentName":"Tacoma","deviceFriendlyName":"Crescent Heights Elementary School","msrDeviceNbr":"2189","readingDateTimeUTC":"2022-05-17 21:24:55","readingDateTimeLocal":"2022-05-17 14:24:55","latitude":47.29472222,"longitude":-122.4,"cellTowerAddress":"","tempC":23.778610229492188,"humidity":34.09271240234375,"pressure":100998.625,"pM25":0.8208824992179871,"pM10":0.8208819627761841,"pM1":0.776276171207428,"vBattery":4.16015625,"cellSignal":-101,"fwVersion":"","aqi":3,"aqiLabel":"Good","calibratedPM25":0.8208824992179871,"calibrationVersion":"None"},{"deploymentName":"Tacoma","deviceFriendlyName":"Crescent Heights Elementary School","msrDeviceNbr":"2189","readingDateTimeUTC":"2022-05-17 21:04:43","readingDateTimeLocal":"2022-05-17 14:04:43","latitude":47.29472222,"longitude":-122.4,"cellTowerAddress":"","tempC":23.810653686523438,"humidity":34.979248046875,"pressure":101009.109375,"pM25":1.4714182615280151,"pM10":1.563733696937561,"pM1":1.3211028575897217,"vBattery":4.162656307220459,"cellSignal":-100,"fwVersion":"","aqi":6,"aqiLabel":"Good","calibratedPM25":1.4714182615280151,"calibrationVersion":"None"},{"deploymentName":"Tacoma","deviceFriendlyName":"Crescent Heights Elementary School","msrDeviceNbr":"2189","readingDateTimeUTC":"2022-05-17 20:44:31","readingDateTimeLocal":"2022-05-17 13:44:31","latitude":47.29472222,"longitude":-122.4,"cellTowerAddress":"","tempC":22.81463623046875,"humidity":37.0635986328125,"pressure":101009.9921875,"pM25":4.603538990020752,"pM10":4.6035356521606445,"pM1":4.353384971618652,"vBattery":4.162968635559082,"cellSignal":-101,"fwVersion":"","aqi":19,"aqiLabel":"Good","calibratedPM25":4.603538990020752,"calibrationVersion":"None"},{"deploymentName":"Tacoma","deviceFriendlyName":"Crescent Heights Elementary School","msrDeviceNbr":"2189","readingDateTimeUTC":"2022-05-17 20:24:19","readingDateTimeLocal":"2022-05-17 13:24:19","latitude":47.29472222,"longitude":-122.4,"cellTowerAddress":"","tempC":21.770553588867188,"humidity":37.6373291015625,"pressure":101043.6015625,"pM25":2.66059947013855,"pM10":2.660597801208496,"pM1":2.516023874282837,"vBattery":4.163280963897705,"cellSignal":-101,"fwVersion":"","aqi":11,"aqiLabel":"Good","calibratedPM25":2.66059947013855,"calibrationVersion":"None"},{"deploymentName":"Tacoma","deviceFriendlyName":"Crescent Heights Elementary School","msrDeviceNbr":"2189","readingDateTimeUTC":"2022-05-17 20:04:07","readingDateTimeLocal":"2022-05-17 13:04:07","latitude":47.29472222,"longitude":-122.4,"cellTowerAddress":"","tempC":20.737152099609375,"humidity":38.38043212890625,"pressure":101033.671875,"pM25":5.510634899139404,"pM10":8.662046432495117,"pM1":2.809293508529663,"vBattery":4.164218425750732,"cellSignal":-100,"fwVersion":"","aqi":22,"aqiLabel":"Good","calibratedPM25":5.510634899139404,"calibrationVersion":"None"},{"deploymentName":"Tacoma","deviceFriendlyName":"Crescent Heights Elementary School","msrDeviceNbr":"2189","readingDateTimeUTC":"2022-05-17 19:43:55","readingDateTimeLocal":"2022-05-17 12:43:55","latitude":47.29472222,"longitude":-122.4,"cellTowerAddress":"","tempC":21.2872314453125,"humidity":38.0950927734375,"pressure":101051.0625,"pM25":5.145442962646484,"pM10":7.841285705566406,"pM1":2.8111636638641357,"vBattery":4.163593769073486,"cellSignal":-101,"fwVersion":"","aqi":21,"aqiLabel":"Good","calibratedPM25":5.145442962646484,"calibrationVersion":"None"},{"deploymentName":"Tacoma","deviceFriendlyName":"Crescent Heights Elementary School","msrDeviceNbr":"2189","readingDateTimeUTC":"2022-05-17 19:23:43","readingDateTimeLocal":"2022-05-17 12:23:43","latitude":47.29472222,"longitude":-122.4,"cellTowerAddress":"","tempC":21.265869140625,"humidity":36.86370849609375,"pressure":101038.6015625,"pM25":2.017470121383667,"pM10":2.6668426990509033,"pM1":1.4129115343093872,"vBattery":4.163906097412109,"cellSignal":-101,"fwVersion":"","aqi":8,"aqiLabel":"Good","calibratedPM25":2.017470121383667,"calibrationVersion":"None"},{"deploymentName":"Tacoma","deviceFriendlyName":"Crescent Heights Elementary School","msrDeviceNbr":"2189","readingDateTimeUTC":"2022-05-17 19:03:32","readingDateTimeLocal":"2022-05-17 12:03:32","latitude":47.29472222,"longitude":-122.4,"cellTowerAddress":"","tempC":23.311309814453125,"humidity":34.88616943359375,"pressure":101054.5,"pM25":0.6973984241485596,"pM10":0.6973979473114014,"pM1":0.6595021486282349,"vBattery":4.163749694824219,"cellSignal":-100,"fwVersion":"","aqi":2,"aqiLabel":"Good","calibratedPM25":0.6973984241485596,"calibrationVersion":"None"},{"deploymentName":"Tacoma","deviceFriendlyName":"Crescent Heights Elementary School","msrDeviceNbr":"2189","readingDateTimeUTC":"2022-05-17 18:43:20","readingDateTimeLocal":"2022-05-17 11:43:20","latitude":47.29472222,"longitude":-122.4,"cellTowerAddress":"","tempC":23.693161010742188,"humidity":37.2467041015625,"pressure":101053.1484375,"pM25":1.3947677612304688,"pM10":1.3947668075561523,"pM1":1.3189767599105835,"vBattery":4.163280963897705,"cellSignal":-101,"fwVersion":"","aqi":5,"aqiLabel":"Good","calibratedPM25":1.3947677612304688,"calibrationVersion":"None"},{"deploymentName":"Tacoma","deviceFriendlyName":"Crescent Heights Elementary School","msrDeviceNbr":"2189","readingDateTimeUTC":"2022-05-17 18:23:08","readingDateTimeLocal":"2022-05-17 11:23:08","latitude":47.29472222,"longitude":-122.4,"cellTowerAddress":"","tempC":22.758560180664062,"humidity":37.46795654296875,"pressure":101052.8828125,"pM25":3.334536552429199,"pM10":3.3345344066619873,"pM1":3.153339385986328,"vBattery":4.163593769073486,"cellSignal":-101,"fwVersion":"","aqi":13,"aqiLabel":"Good","calibratedPM25":3.334536552429199,"calibrationVersion":"None"},{"deploymentName":"Tacoma","deviceFriendlyName":"Crescent Heights Elementary School","msrDeviceNbr":"2189","readingDateTimeUTC":"2022-05-17 18:02:56","readingDateTimeLocal":"2022-05-17 11:02:56","latitude":47.29472222,"longitude":-122.4,"cellTowerAddress":"","tempC":23.725204467773438,"humidity":38.1195068359375,"pressure":101031.390625,"pM25":4.400930881500244,"pM10":6.936056613922119,"pM1":2.229599952697754,"vBattery":4.1640625,"cellSignal":-101,"fwVersion":"","aqi":18,"aqiLabel":"Good","calibratedPM25":4.400930881500244,"calibrationVersion":"None"},{"deploymentName":"Tacoma","deviceFriendlyName":"Crescent Heights Elementary School","msrDeviceNbr":"2189","readingDateTimeUTC":"2022-05-17 17:42:44","readingDateTimeLocal":"2022-05-17 10:42:44","latitude":47.29472222,"longitude":-122.4,"cellTowerAddress":"","tempC":24.472885131835938,"humidity":38.494873046875,"pressure":101014.390625,"pM25":3.184215784072876,"pM10":4.371561527252197,"pM1":2.106231451034546,"vBattery":4.162968635559082,"cellSignal":-101,"fwVersion":"","aqi":13,"aqiLabel":"Good","calibratedPM25":3.184215784072876,"calibrationVersion":"None"},{"deploymentName":"Tacoma","deviceFriendlyName":"Crescent Heights Elementary School","msrDeviceNbr":"2189","readingDateTimeUTC":"2022-05-17 17:22:32","readingDateTimeLocal":"2022-05-17 10:22:32","latitude":47.29472222,"longitude":-122.4,"cellTowerAddress":"","tempC":24.488906860351562,"humidity":39.862060546875,"pressure":101005.5625,"pM25":2.903730869293213,"pM10":3.900369882583618,"pM1":1.9863402843475342,"vBattery":4.164531230926514,"cellSignal":-101,"fwVersion":"","aqi":12,"aqiLabel":"Good","calibratedPM25":2.903730869293213,"calibrationVersion":"None"},{"deploymentName":"Tacoma","deviceFriendlyName":"Crescent Heights Elementary School","msrDeviceNbr":"2189","readingDateTimeUTC":"2022-05-17 17:02:22","readingDateTimeLocal":"2022-05-17 10:02:22","latitude":47.29472222,"longitude":-122.4,"cellTowerAddress":"","tempC":23.367385864257812,"humidity":41.05072021484375,"pressure":101003.0546875,"pM25":2.233509063720703,"pM10":2.914811849594116,"pM1":1.5928754806518555,"vBattery":4.164218425750732,"cellSignal":-101,"fwVersion":"","aqi":9,"aqiLabel":"Good","calibratedPM25":2.233509063720703,"calibrationVersion":"None"},{"deploymentName":"Tacoma","deviceFriendlyName":"Crescent Heights Elementary School","msrDeviceNbr":"2189","readingDateTimeUTC":"2022-05-17 16:42:10","readingDateTimeLocal":"2022-05-17 09:42:10","latitude":47.29472222,"longitude":-122.4,"cellTowerAddress":"","tempC":22.0135498046875,"humidity":46.36383056640625,"pressure":100984.8125,"pM25":3.3448028564453125,"pM10":3.3448004722595215,"pM1":3.1630477905273438,"vBattery":4.165625095367432,"cellSignal":-100,"fwVersion":"","aqi":13,"aqiLabel":"Good","calibratedPM25":3.3448028564453125,"calibrationVersion":"None"},{"deploymentName":"Tacoma","deviceFriendlyName":"Crescent Heights Elementary School","msrDeviceNbr":"2189","readingDateTimeUTC":"2022-05-17 16:21:58","readingDateTimeLocal":"2022-05-17 09:21:58","latitude":47.29472222,"longitude":-122.4,"cellTowerAddress":"","tempC":20.2618408203125,"humidity":48.0743408203125,"pressure":100976.078125,"pM25":2.710632801055908,"pM10":2.7106308937072754,"pM1":2.563338279724121,"vBattery":4.165781021118164,"cellSignal":-100,"fwVersion":"","aqi":11,"aqiLabel":"Good","calibratedPM25":2.710632801055908,"calibrationVersion":"None"}]